{"correlations":[{"variable":"unemployment_rate","label":"Unemployment Rate","spearman":0.4706,"r_squared":0.0243,"slope":9.7514,"intercept":37.825,"n":4988,"significant":true,"description":"Areas with higher unemployment rate consistently show higher crime rates","scatterSample":[{"x":4.6,"y":50.95},{"x":4.3,"y":54.02},{"x":6.9,"y":78.29},{"x":5.3,"y":91.16},{"x":6.2,"y":141.61},{"x":6.0,"y":128.08},{"x":6.5,"y":56.0},{"x":5.7,"y":56.85},{"x":6.2,"y":55.76},{"x":4.8,"y":98.95},{"x":4.9,"y":70.63},{"x":4.9,"y":88.28},{"x":5.6,"y":41.98},{"x":4.3,"y":62.84},{"x":3.3,"y":69.49},{"x":6.4,"y":115.63},{"x":3.4,"y":59.49},{"x":5.2,"y":84.47},{"x":3.0,"y":39.13},{"x":2.5,"y":70.98},{"x":4.6,"y":49.16},{"x":1.7,"y":79.95},{"x":2.6,"y":40.07},{"x":4.9,"y":44.33},{"x":3.2,"y":69.14},{"x":3.8,"y":46.22},{"x":4.4,"y":100.8},{"x":4.6,"y":56.33},{"x":3.4,"y":33.01},{"x":1.9,"y":35.16},{"x":4.0,"y":38.76},{"x":4.1,"y":41.52},{"x":3.3,"y":21.82},{"x":5.6,"y":57.68},{"x":3.2,"y":43.15},{"x":4.3,"y":85.03},{"x":2.9,"y":22.97},{"x":2.3,"y":28.54},{"x":3.7,"y":211.52},{"x":3.3,"y":30.69},{"x":3.3,"y":45.56},{"x":1.9,"y":26.44},{"x":5.3,"y":28.88},{"x":2.4,"y":43.85},{"x":5.5,"y":139.79},{"x":2.4,"y":10.56},{"x":6.1,"y":112.08},{"x":2.4,"y":35.93},{"x":3.3,"y":29.11},{"x":4.1,"y":79.84},{"x":5.5,"y":27.31},{"x":3.5,"y":39.69},{"x":6.6,"y":134.39},{"x":6.6,"y":51.7},{"x":5.3,"y":203.35},{"x":4.6,"y":50.17},{"x":7.8,"y":86.38},{"x":2.9,"y":34.79},{"x":5.7,"y":58.47},{"x":5.3,"y":95.03},{"x":3.4,"y":45.0},{"x":4.3,"y":40.55},{"x":4.8,"y":37.9},{"x":6.4,"y":73.39},{"x":3.6,"y":31.65},{"x":5.8,"y":45.9},{"x":6.4,"y":86.62},{"x":5.0,"y":59.25},{"x":1.7,"y":40.0},{"x":2.5,"y":28.48},{"x":3.6,"y":42.09},{"x":2.8,"y":47.31},{"x":3.5,"y":25.81},{"x":3.1,"y":63.47},{"x":4.1,"y":35.42},{"x":3.3,"y":49.17},{"x":4.0,"y":179.58},{"x":3.7,"y":146.28},{"x":3.3,"y":91.88},{"x":2.2,"y":63.58},{"x":2.4,"y":75.53},{"x":3.3,"y":71.11},{"x":2.6,"y":61.17},{"x":3.6,"y":26.33},{"x":2.6,"y":18.59},{"x":4.5,"y":44.91},{"x":2.6,"y":30.72},{"x":4.1,"y":53.31},{"x":2.1,"y":23.5},{"x":2.0,"y":32.19},{"x":3.3,"y":73.42},{"x":3.2,"y":79.46},{"x":3.9,"y":73.02},{"x":2.8,"y":41.78},{"x":7.0,"y":48.02},{"x":4.2,"y":238.97},{"x":6.1,"y":73.5},{"x":5.3,"y":193.74},{"x":7.3,"y":51.51},{"x":7.2,"y":64.11},{"x":4.8,"y":186.33},{"x":7.1,"y":76.52},{"x":2.9,"y":35.29},{"x":4.5,"y":66.52},{"x":4.6,"y":55.73},{"x":5.0,"y":60.34},{"x":4.5,"y":41.56},{"x":5.9,"y":144.97},{"x":2.9,"y":36.44},{"x":2.7,"y":25.41},{"x":5.2,"y":66.82},{"x":7.7,"y":61.39},{"x":4.5,"y":52.44},{"x":4.1,"y":44.26},{"x":4.6,"y":86.12},{"x":4.7,"y":48.84},{"x":4.5,"y":200.5},{"x":2.3,"y":61.21},{"x":4.5,"y":112.09},{"x":3.1,"y":62.01},{"x":3.4,"y":29.78},{"x":5.5,"y":61.01},{"x":5.4,"y":100.87},{"x":6.6,"y":70.16},{"x":4.3,"y":92.27},{"x":4.1,"y":61.9},{"x":6.0,"y":86.27},{"x":5.1,"y":52.32},{"x":10.2,"y":76.05},{"x":6.4,"y":104.52},{"x":2.6,"y":33.71},{"x":4.6,"y":67.61},{"x":4.8,"y":83.87},{"x":4.8,"y":38.92},{"x":5.8,"y":42.28},{"x":2.7,"y":47.16},{"x":4.5,"y":28.41},{"x":5.0,"y":50.51},{"x":4.2,"y":37.77},{"x":4.1,"y":52.77},{"x":5.2,"y":74.91},{"x":6.2,"y":99.68},{"x":4.0,"y":50.52},{"x":4.5,"y":50.63},{"x":4.9,"y":121.11},{"x":5.8,"y":46.14},{"x":7.0,"y":52.45},{"x":4.2,"y":33.76},{"x":4.8,"y":56.71},{"x":2.8,"y":66.58},{"x":5.0,"y":69.81},{"x":3.0,"y":70.69},{"x":6.6,"y":186.93},{"x":4.7,"y":62.6},{"x":5.6,"y":47.9},{"x":3.0,"y":53.57},{"x":6.8,"y":58.56},{"x":4.1,"y":41.35},{"x":5.1,"y":59.8},{"x":4.9,"y":58.88},{"x":6.0,"y":104.95},{"x":4.0,"y":92.67},{"x":4.1,"y":51.18},{"x":3.0,"y":30.66},{"x":5.3,"y":85.52},{"x":6.8,"y":84.36},{"x":6.2,"y":202.62},{"x":2.3,"y":48.83},{"x":5.3,"y":82.3},{"x":3.5,"y":48.39},{"x":5.9,"y":60.31},{"x":3.6,"y":62.62},{"x":3.0,"y":81.04},{"x":4.1,"y":74.16},{"x":7.7,"y":69.2},{"x":4.7,"y":64.34},{"x":3.6,"y":72.93},{"x":5.1,"y":113.61},{"x":4.1,"y":77.71},{"x":8.3,"y":79.49},{"x":7.9,"y":59.93},{"x":5.4,"y":99.55},{"x":7.8,"y":58.87},{"x":5.6,"y":120.38},{"x":4.8,"y":97.13},{"x":6.0,"y":52.37},{"x":6.0,"y":93.91},{"x":6.8,"y":145.08},{"x":4.7,"y":61.48},{"x":2.6,"y":45.82},{"x":3.5,"y":154.22},{"x":5.9,"y":89.93},{"x":2.6,"y":83.71},{"x":7.6,"y":75.48},{"x":5.5,"y":171.17},{"x":4.3,"y":105.17},{"x":4.6,"y":60.57},{"x":6.8,"y":103.54},{"x":5.5,"y":141.11},{"x":5.8,"y":89.2},{"x":4.6,"y":54.32},{"x":7.6,"y":65.5},{"x":5.7,"y":204.97},{"x":4.0,"y":75.67},{"x":6.6,"y":115.08},{"x":3.8,"y":42.77},{"x":8.5,"y":70.72},{"x":3.8,"y":54.18},{"x":6.9,"y":91.54},{"x":3.6,"y":47.47},{"x":4.3,"y":36.48},{"x":7.2,"y":134.14},{"x":4.3,"y":44.09},{"x":4.4,"y":168.82},{"x":6.8,"y":281.43},{"x":6.4,"y":88.91},{"x":3.1,"y":37.69},{"x":4.6,"y":55.06},{"x":7.6,"y":208.46},{"x":5.9,"y":182.46},{"x":5.7,"y":96.71},{"x":5.3,"y":57.33},{"x":5.5,"y":149.81},{"x":3.7,"y":48.88},{"x":5.1,"y":44.06},{"x":4.2,"y":76.46},{"x":5.2,"y":33.72},{"x":2.0,"y":30.96},{"x":4.3,"y":41.52},{"x":3.6,"y":34.06},{"x":3.3,"y":38.96},{"x":2.2,"y":35.13},{"x":3.2,"y":29.3},{"x":3.6,"y":74.69},{"x":5.0,"y":117.1},{"x":3.5,"y":35.54},{"x":6.0,"y":30.75},{"x":3.0,"y":50.52},{"x":1.8,"y":13.83},{"x":3.1,"y":39.12},{"x":2.3,"y":34.83},{"x":5.2,"y":58.86},{"x":3.9,"y":38.12},{"x":4.2,"y":72.55},{"x":3.9,"y":44.88},{"x":2.2,"y":26.02},{"x":4.3,"y":42.03},{"x":4.0,"y":60.99},{"x":3.6,"y":45.21},{"x":4.2,"y":442.65},{"x":4.4,"y":38.76},{"x":4.4,"y":96.27},{"x":2.5,"y":47.59},{"x":5.2,"y":67.14},{"x":4.9,"y":66.54},{"x":5.9,"y":87.52},{"x":4.7,"y":88.24},{"x":2.6,"y":9.71},{"x":3.2,"y":45.45},{"x":8.8,"y":102.98},{"x":2.6,"y":26.44},{"x":2.1,"y":25.56},{"x":2.3,"y":19.63},{"x":4.1,"y":101.43},{"x":5.0,"y":47.78},{"x":6.5,"y":264.72},{"x":3.4,"y":38.17},{"x":6.6,"y":95.34},{"x":3.1,"y":59.83},{"x":6.3,"y":56.53},{"x":3.7,"y":61.15},{"x":4.1,"y":70.65},{"x":3.7,"y":56.56},{"x":5.4,"y":41.37},{"x":5.2,"y":65.52},{"x":5.2,"y":67.97},{"x":4.5,"y":75.4},{"x":5.5,"y":70.13},{"x":4.2,"y":68.3},{"x":7.2,"y":108.14},{"x":4.8,"y":29.49},{"x":5.7,"y":64.59},{"x":5.1,"y":128.38},{"x":5.0,"y":178.64},{"x":9.0,"y":60.66},{"x":6.5,"y":78.17},{"x":6.6,"y":71.48},{"x":4.9,"y":126.04},{"x":7.8,"y":99.06},{"x":6.9,"y":97.2},{"x":4.5,"y":64.77},{"x":4.7,"y":77.46},{"x":6.5,"y":87.44},{"x":3.9,"y":70.04},{"x":3.4,"y":65.98},{"x":3.2,"y":81.94},{"x":4.6,"y":81.55},{"x":3.8,"y":106.24},{"x":3.5,"y":96.72},{"x":2.4,"y":52.63},{"x":3.8,"y":119.17},{"x":7.1,"y":151.43},{"x":3.2,"y":187.03},{"x":4.0,"y":75.84},{"x":4.9,"y":161.6},{"x":3.1,"y":82.95},{"x":4.5,"y":447.8},{"x":3.0,"y":178.99},{"x":2.7,"y":29.5},{"x":3.2,"y":74.88},{"x":3.9,"y":43.74},{"x":3.6,"y":68.29},{"x":5.5,"y":56.71},{"x":4.9,"y":43.37},{"x":2.9,"y":50.4},{"x":3.7,"y":55.21},{"x":3.1,"y":26.02},{"x":4.1,"y":53.49},{"x":3.9,"y":70.88},{"x":5.6,"y":90.99},{"x":3.0,"y":110.34},{"x":2.7,"y":155.24},{"x":8.2,"y":74.04},{"x":5.8,"y":56.89},{"x":4.9,"y":82.67},{"x":6.8,"y":69.35},{"x":4.2,"y":49.1},{"x":7.4,"y":108.4},{"x":7.3,"y":243.99},{"x":5.4,"y":72.38},{"x":6.1,"y":55.67},{"x":3.7,"y":73.95},{"x":4.2,"y":41.8},{"x":5.0,"y":53.53},{"x":2.7,"y":35.71},{"x":2.4,"y":56.25},{"x":7.2,"y":124.42},{"x":9.6,"y":48.68},{"x":6.1,"y":105.26},{"x":10.1,"y":108.85},{"x":6.0,"y":57.06},{"x":5.6,"y":68.02},{"x":4.5,"y":114.12},{"x":5.5,"y":72.91},{"x":8.0,"y":61.43},{"x":4.8,"y":47.84},{"x":4.4,"y":34.65},{"x":4.6,"y":51.63},{"x":5.1,"y":80.17},{"x":6.9,"y":78.68},{"x":4.7,"y":96.92},{"x":4.9,"y":139.34},{"x":4.4,"y":56.67},{"x":8.9,"y":93.24},{"x":10.8,"y":88.57},{"x":3.0,"y":52.23},{"x":2.6,"y":15.48},{"x":5.1,"y":98.37},{"x":3.5,"y":21.98},{"x":4.8,"y":55.56},{"x":3.6,"y":75.32},{"x":4.8,"y":48.16},{"x":3.3,"y":20.9},{"x":4.3,"y":46.01},{"x":3.4,"y":52.0},{"x":5.0,"y":87.06},{"x":5.0,"y":256.55},{"x":1.9,"y":40.4},{"x":1.8,"y":36.9},{"x":5.6,"y":42.65},{"x":4.7,"y":47.23},{"x":6.1,"y":72.28},{"x":6.5,"y":92.11},{"x":6.5,"y":81.89},{"x":6.8,"y":48.21},{"x":6.0,"y":70.3},{"x":6.0,"y":67.0},{"x":5.5,"y":48.42},{"x":6.0,"y":158.81},{"x":5.7,"y":31.22},{"x":5.4,"y":52.56},{"x":6.1,"y":27.41},{"x":5.1,"y":77.04},{"x":7.4,"y":76.88},{"x":6.1,"y":41.65},{"x":4.2,"y":28.01},{"x":3.9,"y":58.46},{"x":3.8,"y":49.54},{"x":3.1,"y":56.81},{"x":3.4,"y":39.66},{"x":5.2,"y":87.95},{"x":5.7,"y":131.94},{"x":2.9,"y":42.3},{"x":6.5,"y":70.4},{"x":3.8,"y":49.43},{"x":9.3,"y":88.67},{"x":2.3,"y":30.28},{"x":4.8,"y":33.72},{"x":3.5,"y":65.67},{"x":4.5,"y":58.92},{"x":5.2,"y":144.7},{"x":3.8,"y":50.07},{"x":2.8,"y":65.48},{"x":3.4,"y":34.92},{"x":3.3,"y":68.95},{"x":4.0,"y":61.17},{"x":3.2,"y":45.01},{"x":2.6,"y":59.51},{"x":4.1,"y":109.46},{"x":2.9,"y":39.28},{"x":3.4,"y":53.61},{"x":7.9,"y":19.77},{"x":3.5,"y":23.35},{"x":2.7,"y":51.89},{"x":3.0,"y":45.73},{"x":5.0,"y":58.36},{"x":7.0,"y":82.32},{"x":6.2,"y":51.39},{"x":4.5,"y":65.68},{"x":2.9,"y":35.2},{"x":7.1,"y":191.4},{"x":5.8,"y":103.27},{"x":6.2,"y":80.06},{"x":5.2,"y":110.06},{"x":3.0,"y":77.56},{"x":6.7,"y":96.36},{"x":6.8,"y":76.54},{"x":3.4,"y":58.3},{"x":5.0,"y":51.09},{"x":4.7,"y":81.92},{"x":3.1,"y":34.85},{"x":3.2,"y":34.56},{"x":2.6,"y":35.1},{"x":2.9,"y":45.84},{"x":3.1,"y":37.34},{"x":3.2,"y":65.23},{"x":4.2,"y":146.51},{"x":4.0,"y":86.85},{"x":3.4,"y":45.48},{"x":3.8,"y":64.42},{"x":3.2,"y":76.58},{"x":3.9,"y":56.58},{"x":4.8,"y":73.24},{"x":3.9,"y":25.66},{"x":7.0,"y":177.54},{"x":7.4,"y":56.17},{"x":3.5,"y":66.26},{"x":5.6,"y":101.96},{"x":6.9,"y":70.52},{"x":7.2,"y":107.56},{"x":4.5,"y":30.7},{"x":4.8,"y":128.61},{"x":8.1,"y":90.85},{"x":8.4,"y":139.04},{"x":5.4,"y":101.41},{"x":5.6,"y":66.63},{"x":5.0,"y":101.87},{"x":2.9,"y":48.02},{"x":2.9,"y":43.48},{"x":4.5,"y":52.93},{"x":4.9,"y":55.16},{"x":3.5,"y":23.63},{"x":5.1,"y":46.62},{"x":7.3,"y":57.11},{"x":3.2,"y":65.6},{"x":7.4,"y":66.13},{"x":5.7,"y":87.6},{"x":4.6,"y":81.43},{"x":3.6,"y":99.63},{"x":4.4,"y":56.05},{"x":6.2,"y":61.94},{"x":3.1,"y":55.78},{"x":3.5,"y":60.85},{"x":3.0,"y":33.2},{"x":2.2,"y":63.44},{"x":6.5,"y":73.39},{"x":2.8,"y":100.28},{"x":8.8,"y":94.24},{"x":2.7,"y":27.98},{"x":2.5,"y":64.63},{"x":4.7,"y":80.58},{"x":4.1,"y":100.95},{"x":2.6,"y":112.87},{"x":4.0,"y":68.25},{"x":2.0,"y":79.54},{"x":4.5,"y":104.87},{"x":3.0,"y":56.43},{"x":5.4,"y":65.95},{"x":3.8,"y":58.58},{"x":3.4,"y":56.01},{"x":6.6,"y":334.87},{"x":7.8,"y":60.49},{"x":6.1,"y":205.79},{"x":3.3,"y":147.32},{"x":2.9,"y":93.28},{"x":3.4,"y":178.57},{"x":7.4,"y":65.18},{"x":3.2,"y":363.64},{"x":4.2,"y":74.72},{"x":4.5,"y":83.7},{"x":4.4,"y":2136.41},{"x":4.5,"y":59.19},{"x":4.8,"y":40.36},{"x":3.2,"y":31.76},{"x":10.1,"y":118.17},{"x":4.7,"y":25.27},{"x":4.5,"y":30.21},{"x":6.0,"y":146.87},{"x":5.1,"y":58.42},{"x":4.8,"y":35.0},{"x":6.3,"y":133.09},{"x":4.3,"y":105.12},{"x":6.0,"y":189.33},{"x":8.0,"y":48.42},{"x":5.1,"y":97.8},{"x":4.8,"y":130.76},{"x":6.5,"y":137.56},{"x":3.7,"y":144.32},{"x":4.5,"y":192.69},{"x":5.7,"y":118.39},{"x":10.1,"y":148.15},{"x":5.1,"y":51.3},{"x":5.5,"y":34.59},{"x":7.6,"y":74.1},{"x":8.1,"y":59.99},{"x":5.6,"y":110.82},{"x":5.7,"y":91.67},{"x":5.6,"y":96.45},{"x":5.7,"y":287.47},{"x":6.9,"y":97.04},{"x":4.8,"y":101.5},{"x":5.7,"y":32.87},{"x":4.2,"y":54.6},{"x":5.1,"y":61.85},{"x":4.2,"y":58.36},{"x":4.8,"y":27.45},{"x":4.6,"y":36.75},{"x":5.3,"y":51.37},{"x":6.8,"y":58.05},{"x":6.4,"y":55.06},{"x":4.0,"y":77.48},{"x":5.2,"y":92.85},{"x":6.8,"y":125.0},{"x":4.7,"y":136.12},{"x":5.4,"y":162.13},{"x":6.1,"y":88.95},{"x":4.7,"y":176.11},{"x":3.9,"y":80.03},{"x":8.1,"y":85.76},{"x":11.4,"y":91.14},{"x":6.3,"y":81.98},{"x":7.4,"y":127.88},{"x":7.4,"y":84.01},{"x":8.1,"y":89.95},{"x":6.0,"y":148.26}]},{"variable":"youth_share","label":"Age 20-24 Share","spearman":0.401,"r_squared":0.0945,"slope":10.8962,"intercept":12.0341,"n":4988,"significant":true,"description":"Areas with higher age 20-24 share consistently show higher crime rates","scatterSample":[{"x":6.7,"y":50.95},{"x":6.0,"y":54.02},{"x":5.8,"y":78.29},{"x":7.5,"y":91.16},{"x":5.9,"y":141.61},{"x":6.4,"y":128.08},{"x":5.1,"y":56.0},{"x":6.1,"y":56.85},{"x":4.7,"y":55.76},{"x":5.3,"y":98.95},{"x":5.3,"y":70.63},{"x":6.2,"y":88.28},{"x":8.8,"y":41.98},{"x":7.2,"y":62.84},{"x":6.4,"y":69.49},{"x":5.2,"y":115.63},{"x":4.1,"y":59.49},{"x":5.7,"y":84.47},{"x":3.5,"y":39.13},{"x":4.1,"y":70.98},{"x":5.0,"y":49.16},{"x":4.4,"y":79.95},{"x":5.5,"y":40.07},{"x":5.6,"y":44.33},{"x":5.3,"y":69.14},{"x":5.5,"y":46.22},{"x":5.8,"y":100.8},{"x":6.0,"y":56.33},{"x":3.6,"y":33.01},{"x":4.9,"y":35.16},{"x":6.8,"y":38.76},{"x":4.7,"y":41.52},{"x":6.6,"y":21.82},{"x":6.6,"y":57.68},{"x":4.9,"y":43.15},{"x":4.8,"y":85.03},{"x":4.8,"y":22.97},{"x":5.8,"y":28.54},{"x":5.0,"y":211.52},{"x":4.2,"y":30.69},{"x":6.5,"y":45.56},{"x":3.8,"y":26.44},{"x":5.3,"y":28.88},{"x":4.2,"y":43.85},{"x":6.0,"y":139.79},{"x":3.9,"y":10.56},{"x":6.4,"y":112.08},{"x":3.3,"y":35.93},{"x":5.3,"y":29.11},{"x":10.7,"y":79.84},{"x":6.9,"y":27.31},{"x":6.7,"y":39.69},{"x":7.8,"y":134.39},{"x":9.5,"y":51.7},{"x":7.5,"y":203.35},{"x":6.8,"y":50.17},{"x":6.7,"y":86.38},{"x":5.6,"y":34.79},{"x":5.2,"y":58.47},{"x":6.3,"y":95.03},{"x":5.1,"y":45.0},{"x":7.7,"y":40.55},{"x":4.5,"y":37.9},{"x":6.8,"y":73.39},{"x":9.5,"y":31.65},{"x":7.0,"y":45.9},{"x":6.7,"y":86.62},{"x":7.2,"y":59.25},{"x":4.1,"y":40.0},{"x":4.6,"y":28.48},{"x":5.2,"y":42.09},{"x":3.5,"y":47.31},{"x":4.6,"y":25.81},{"x":4.0,"y":63.47},{"x":3.5,"y":35.42},{"x":3.1,"y":49.17},{"x":4.2,"y":179.58},{"x":4.4,"y":146.28},{"x":5.2,"y":91.88},{"x":4.6,"y":63.58},{"x":5.4,"y":75.53},{"x":5.4,"y":71.11},{"x":4.3,"y":61.17},{"x":3.2,"y":26.33},{"x":4.1,"y":18.59},{"x":4.1,"y":44.91},{"x":2.6,"y":30.72},{"x":3.2,"y":53.31},{"x":3.6,"y":23.5},{"x":3.9,"y":32.19},{"x":5.7,"y":73.42},{"x":3.7,"y":79.46},{"x":6.1,"y":73.02},{"x":4.1,"y":41.78},{"x":7.4,"y":48.02},{"x":4.9,"y":238.97},{"x":5.0,"y":73.5},{"x":14.9,"y":193.74},{"x":11.5,"y":51.51},{"x":7.4,"y":64.11},{"x":10.6,"y":186.33},{"x":9.4,"y":76.52},{"x":4.8,"y":35.29},{"x":4.8,"y":66.52},{"x":6.6,"y":55.73},{"x":5.7,"y":60.34},{"x":5.3,"y":41.56},{"x":6.4,"y":144.97},{"x":4.0,"y":36.44},{"x":5.5,"y":25.41},{"x":5.1,"y":66.82},{"x":7.9,"y":61.39},{"x":6.3,"y":52.44},{"x":5.6,"y":44.26},{"x":6.9,"y":86.12},{"x":7.3,"y":48.84},{"x":4.5,"y":200.5},{"x":5.3,"y":61.21},{"x":6.5,"y":112.09},{"x":5.4,"y":62.01},{"x":5.1,"y":29.78},{"x":5.8,"y":61.01},{"x":6.3,"y":100.87},{"x":7.5,"y":70.16},{"x":3.6,"y":92.27},{"x":6.4,"y":61.9},{"x":5.9,"y":86.27},{"x":5.4,"y":52.32},{"x":7.0,"y":76.05},{"x":5.8,"y":104.52},{"x":4.3,"y":33.71},{"x":6.3,"y":67.61},{"x":4.6,"y":83.87},{"x":3.4,"y":38.92},{"x":7.8,"y":42.28},{"x":7.2,"y":47.16},{"x":4.1,"y":28.41},{"x":6.1,"y":50.51},{"x":3.4,"y":37.77},{"x":6.0,"y":52.77},{"x":5.5,"y":74.91},{"x":7.6,"y":99.68},{"x":7.7,"y":50.52},{"x":7.8,"y":50.63},{"x":5.0,"y":121.11},{"x":6.1,"y":46.14},{"x":6.5,"y":52.45},{"x":3.2,"y":33.76},{"x":5.3,"y":56.71},{"x":5.5,"y":66.58},{"x":5.9,"y":69.81},{"x":4.0,"y":70.69},{"x":6.7,"y":186.93},{"x":6.9,"y":62.6},{"x":6.7,"y":47.9},{"x":4.4,"y":53.57},{"x":9.5,"y":58.56},{"x":5.3,"y":41.35},{"x":6.2,"y":59.8},{"x":7.4,"y":58.88},{"x":5.8,"y":104.95},{"x":4.3,"y":92.67},{"x":3.5,"y":51.18},{"x":3.8,"y":30.66},{"x":3.2,"y":85.52},{"x":5.7,"y":84.36},{"x":7.0,"y":202.62},{"x":4.3,"y":48.83},{"x":6.3,"y":82.3},{"x":3.1,"y":48.39},{"x":5.3,"y":60.31},{"x":4.7,"y":62.62},{"x":5.5,"y":81.04},{"x":5.6,"y":74.16},{"x":7.3,"y":69.2},{"x":6.4,"y":64.34},{"x":7.9,"y":72.93},{"x":6.5,"y":113.61},{"x":5.2,"y":77.71},{"x":5.2,"y":79.49},{"x":9.7,"y":59.93},{"x":5.3,"y":99.55},{"x":8.3,"y":58.87},{"x":8.1,"y":120.38},{"x":7.1,"y":97.13},{"x":6.8,"y":52.37},{"x":4.4,"y":93.91},{"x":12.3,"y":145.08},{"x":5.1,"y":61.48},{"x":6.8,"y":45.82},{"x":10.2,"y":154.22},{"x":8.9,"y":89.93},{"x":4.6,"y":83.71},{"x":5.5,"y":75.48},{"x":5.6,"y":171.17},{"x":5.6,"y":105.17},{"x":6.3,"y":60.57},{"x":9.5,"y":103.54},{"x":11.6,"y":141.11},{"x":9.5,"y":89.2},{"x":12.6,"y":54.32},{"x":11.0,"y":65.5},{"x":8.2,"y":204.97},{"x":3.9,"y":75.67},{"x":6.5,"y":115.08},{"x":9.0,"y":42.77},{"x":10.1,"y":70.72},{"x":3.1,"y":54.18},{"x":5.9,"y":91.54},{"x":2.5,"y":47.47},{"x":4.8,"y":36.48},{"x":7.7,"y":134.14},{"x":2.4,"y":44.09},{"x":5.3,"y":168.82},{"x":8.6,"y":281.43},{"x":5.7,"y":88.91},{"x":5.0,"y":37.69},{"x":4.2,"y":55.06},{"x":7.9,"y":208.46},{"x":6.7,"y":182.46},{"x":6.6,"y":96.71},{"x":8.3,"y":57.33},{"x":6.3,"y":149.81},{"x":5.2,"y":48.88},{"x":6.6,"y":44.06},{"x":6.0,"y":76.46},{"x":6.6,"y":33.72},{"x":2.4,"y":30.96},{"x":5.9,"y":41.52},{"x":6.6,"y":34.06},{"x":5.0,"y":38.96},{"x":4.2,"y":35.13},{"x":8.1,"y":29.3},{"x":6.4,"y":74.69},{"x":6.1,"y":117.1},{"x":6.7,"y":35.54},{"x":8.4,"y":30.75},{"x":6.2,"y":50.52},{"x":5.9,"y":13.83},{"x":4.4,"y":39.12},{"x":5.6,"y":34.83},{"x":6.5,"y":58.86},{"x":4.9,"y":38.12},{"x":6.1,"y":72.55},{"x":4.7,"y":44.88},{"x":5.6,"y":26.02},{"x":5.5,"y":42.03},{"x":5.5,"y":60.99},{"x":5.6,"y":45.21},{"x":6.5,"y":442.65},{"x":5.0,"y":38.76},{"x":5.7,"y":96.27},{"x":4.6,"y":47.59},{"x":6.0,"y":67.14},{"x":6.3,"y":66.54},{"x":6.8,"y":87.52},{"x":7.0,"y":88.24},{"x":5.2,"y":9.71},{"x":4.7,"y":45.45},{"x":5.3,"y":102.98},{"x":4.6,"y":26.44},{"x":3.9,"y":25.56},{"x":3.6,"y":19.63},{"x":5.3,"y":101.43},{"x":5.5,"y":47.78},{"x":5.2,"y":264.72},{"x":4.8,"y":38.17},{"x":7.7,"y":95.34},{"x":3.1,"y":59.83},{"x":6.2,"y":56.53},{"x":4.9,"y":61.15},{"x":3.9,"y":70.65},{"x":5.3,"y":56.56},{"x":6.2,"y":41.37},{"x":6.9,"y":65.52},{"x":5.3,"y":67.97},{"x":4.5,"y":75.4},{"x":6.5,"y":70.13},{"x":6.6,"y":68.3},{"x":5.8,"y":108.14},{"x":7.1,"y":29.49},{"x":6.1,"y":64.59},{"x":5.7,"y":128.38},{"x":7.5,"y":178.64},{"x":12.1,"y":60.66},{"x":10.9,"y":78.17},{"x":13.8,"y":71.48},{"x":5.1,"y":126.04},{"x":9.3,"y":99.06},{"x":6.8,"y":97.2},{"x":6.6,"y":64.77},{"x":11.6,"y":77.46},{"x":10.7,"y":87.44},{"x":5.3,"y":70.04},{"x":4.2,"y":65.98},{"x":4.1,"y":81.94},{"x":9.4,"y":81.55},{"x":6.2,"y":106.24},{"x":3.9,"y":96.72},{"x":7.5,"y":52.63},{"x":14.0,"y":119.17},{"x":7.1,"y":151.43},{"x":8.4,"y":187.03},{"x":9.3,"y":75.84},{"x":6.4,"y":161.6},{"x":12.2,"y":82.95},{"x":6.5,"y":447.8},{"x":5.4,"y":178.99},{"x":3.6,"y":29.5},{"x":3.8,"y":74.88},{"x":6.1,"y":43.74},{"x":6.4,"y":68.29},{"x":11.4,"y":56.71},{"x":10.4,"y":43.37},{"x":6.7,"y":50.4},{"x":4.8,"y":55.21},{"x":3.5,"y":26.02},{"x":4.2,"y":53.49},{"x":3.8,"y":70.88},{"x":8.5,"y":90.99},{"x":11.9,"y":110.34},{"x":9.7,"y":155.24},{"x":8.2,"y":74.04},{"x":11.6,"y":56.89},{"x":5.4,"y":82.67},{"x":7.9,"y":69.35},{"x":5.0,"y":49.1},{"x":7.7,"y":108.4},{"x":12.0,"y":243.99},{"x":6.1,"y":72.38},{"x":8.8,"y":55.67},{"x":6.1,"y":73.95},{"x":5.0,"y":41.8},{"x":4.4,"y":53.53},{"x":4.6,"y":35.71},{"x":3.8,"y":56.25},{"x":8.8,"y":124.42},{"x":8.9,"y":48.68},{"x":4.9,"y":105.26},{"x":5.6,"y":108.85},{"x":6.5,"y":57.06},{"x":5.6,"y":68.02},{"x":5.7,"y":114.12},{"x":5.7,"y":72.91},{"x":8.2,"y":61.43},{"x":4.1,"y":47.84},{"x":6.3,"y":34.65},{"x":6.3,"y":51.63},{"x":5.3,"y":80.17},{"x":8.1,"y":78.68},{"x":5.5,"y":96.92},{"x":6.1,"y":139.34},{"x":4.4,"y":56.67},{"x":8.5,"y":93.24},{"x":6.7,"y":88.57},{"x":4.6,"y":52.23},{"x":4.6,"y":15.48},{"x":4.6,"y":98.37},{"x":4.6,"y":21.98},{"x":5.7,"y":55.56},{"x":3.0,"y":75.32},{"x":3.8,"y":48.16},{"x":4.5,"y":20.9},{"x":5.9,"y":46.01},{"x":6.5,"y":52.0},{"x":5.0,"y":87.06},{"x":4.9,"y":256.55},{"x":5.4,"y":40.4},{"x":3.8,"y":36.9},{"x":6.8,"y":42.65},{"x":6.0,"y":47.23},{"x":7.1,"y":72.28},{"x":7.8,"y":92.11},{"x":6.3,"y":81.89},{"x":8.3,"y":48.21},{"x":7.0,"y":70.3},{"x":7.0,"y":67.0},{"x":7.0,"y":48.42},{"x":8.0,"y":158.81},{"x":6.7,"y":31.22},{"x":6.2,"y":52.56},{"x":4.7,"y":27.41},{"x":7.4,"y":77.04},{"x":8.3,"y":76.88},{"x":10.2,"y":41.65},{"x":8.0,"y":28.01},{"x":7.8,"y":58.46},{"x":5.0,"y":49.54},{"x":3.3,"y":56.81},{"x":7.1,"y":39.66},{"x":6.7,"y":87.95},{"x":6.0,"y":131.94},{"x":5.1,"y":42.3},{"x":7.3,"y":70.4},{"x":4.9,"y":49.43},{"x":8.5,"y":88.67},{"x":4.1,"y":30.28},{"x":6.8,"y":33.72},{"x":5.5,"y":65.67},{"x":6.4,"y":58.92},{"x":6.8,"y":144.7},{"x":5.0,"y":50.07},{"x":3.2,"y":65.48},{"x":3.1,"y":34.92},{"x":3.5,"y":68.95},{"x":4.4,"y":61.17},{"x":4.2,"y":45.01},{"x":4.4,"y":59.51},{"x":3.2,"y":109.46},{"x":3.2,"y":39.28},{"x":3.8,"y":53.61},{"x":18.4,"y":19.77},{"x":4.7,"y":23.35},{"x":2.5,"y":51.89},{"x":5.7,"y":45.73},{"x":6.3,"y":58.36},{"x":8.5,"y":82.32},{"x":13.6,"y":51.39},{"x":2.8,"y":65.68},{"x":3.7,"y":35.2},{"x":7.6,"y":191.4},{"x":6.7,"y":103.27},{"x":5.9,"y":80.06},{"x":5.5,"y":110.06},{"x":13.1,"y":77.56},{"x":7.7,"y":96.36},{"x":8.2,"y":76.54},{"x":3.3,"y":58.3},{"x":7.0,"y":51.09},{"x":7.5,"y":81.92},{"x":4.1,"y":34.85},{"x":6.6,"y":34.56},{"x":5.1,"y":35.1},{"x":3.5,"y":45.84},{"x":4.7,"y":37.34},{"x":4.2,"y":65.23},{"x":6.5,"y":146.51},{"x":5.1,"y":86.85},{"x":5.5,"y":45.48},{"x":2.4,"y":64.42},{"x":5.6,"y":76.58},{"x":4.8,"y":56.58},{"x":6.4,"y":73.24},{"x":4.6,"y":25.66},{"x":12.4,"y":177.54},{"x":8.3,"y":56.17},{"x":13.1,"y":66.26},{"x":7.6,"y":101.96},{"x":7.9,"y":70.52},{"x":11.0,"y":107.56},{"x":7.6,"y":30.7},{"x":10.4,"y":128.61},{"x":10.7,"y":90.85},{"x":12.5,"y":139.04},{"x":10.1,"y":101.41},{"x":7.2,"y":66.63},{"x":5.6,"y":101.87},{"x":5.0,"y":48.02},{"x":5.2,"y":43.48},{"x":5.4,"y":52.93},{"x":6.9,"y":55.16},{"x":4.7,"y":23.63},{"x":5.3,"y":46.62},{"x":5.2,"y":57.11},{"x":5.1,"y":65.6},{"x":5.1,"y":66.13},{"x":6.7,"y":87.6},{"x":5.7,"y":81.43},{"x":5.1,"y":99.63},{"x":3.7,"y":56.05},{"x":5.6,"y":61.94},{"x":9.7,"y":55.78},{"x":8.0,"y":60.85},{"x":5.0,"y":33.2},{"x":5.6,"y":63.44},{"x":7.9,"y":73.39},{"x":7.5,"y":100.28},{"x":6.2,"y":94.24},{"x":5.2,"y":27.98},{"x":6.5,"y":64.63},{"x":10.1,"y":80.58},{"x":6.4,"y":100.95},{"x":3.7,"y":112.87},{"x":5.9,"y":68.25},{"x":6.0,"y":79.54},{"x":12.7,"y":104.87},{"x":5.5,"y":56.43},{"x":7.1,"y":65.95},{"x":5.1,"y":58.58},{"x":5.8,"y":56.01},{"x":16.7,"y":334.87},{"x":12.0,"y":60.49},{"x":20.0,"y":205.79},{"x":10.6,"y":147.32},{"x":5.4,"y":93.28},{"x":7.5,"y":178.57},{"x":10.8,"y":65.18},{"x":11.3,"y":363.64},{"x":9.9,"y":74.72},{"x":8.8,"y":83.7},{"x":17.2,"y":2136.41},{"x":5.4,"y":59.19},{"x":5.4,"y":40.36},{"x":7.7,"y":31.76},{"x":9.6,"y":118.17},{"x":4.7,"y":25.27},{"x":4.8,"y":30.21},{"x":3.2,"y":146.87},{"x":8.1,"y":58.42},{"x":3.6,"y":35.0},{"x":9.1,"y":133.09},{"x":7.3,"y":105.12},{"x":4.5,"y":189.33},{"x":9.5,"y":48.42},{"x":8.0,"y":97.8},{"x":5.5,"y":130.76},{"x":8.1,"y":137.56},{"x":4.9,"y":144.32},{"x":19.1,"y":192.69},{"x":6.1,"y":118.39},{"x":5.7,"y":148.15},{"x":6.4,"y":51.3},{"x":6.0,"y":34.59},{"x":6.9,"y":74.1},{"x":5.9,"y":59.99},{"x":5.5,"y":110.82},{"x":4.9,"y":91.67},{"x":5.7,"y":96.45},{"x":10.0,"y":287.47},{"x":6.7,"y":97.04},{"x":4.9,"y":101.5},{"x":5.2,"y":32.87},{"x":5.3,"y":54.6},{"x":7.4,"y":61.85},{"x":14.5,"y":58.36},{"x":8.6,"y":27.45},{"x":7.9,"y":36.75},{"x":5.7,"y":51.37},{"x":5.6,"y":58.05},{"x":6.3,"y":55.06},{"x":6.3,"y":77.48},{"x":4.7,"y":92.85},{"x":6.5,"y":125.0},{"x":22.9,"y":136.12},{"x":7.9,"y":162.13},{"x":6.0,"y":88.95},{"x":7.9,"y":176.11},{"x":3.9,"y":80.03},{"x":8.0,"y":85.76},{"x":9.3,"y":91.14},{"x":6.4,"y":81.98},{"x":9.2,"y":127.88},{"x":30.5,"y":84.01},{"x":17.7,"y":89.95},{"x":5.7,"y":148.26}]},{"variable":"private_renting_rate","label":"Private Renting Rate","spearman":0.3787,"r_squared":0.0839,"slope":2.1751,"intercept":21.1898,"n":4988,"significant":true,"description":"Areas with higher private renting rate consistently show higher crime rates","scatterSample":[{"x":46.5,"y":50.95},{"x":17.7,"y":54.02},{"x":13.9,"y":78.29},{"x":28.7,"y":91.16},{"x":22.3,"y":141.61},{"x":16.3,"y":128.08},{"x":18.3,"y":56.0},{"x":19.5,"y":56.85},{"x":19.9,"y":55.76},{"x":15.9,"y":98.95},{"x":21.0,"y":70.63},{"x":36.4,"y":88.28},{"x":10.7,"y":41.98},{"x":36.0,"y":62.84},{"x":44.9,"y":69.49},{"x":16.0,"y":115.63},{"x":35.9,"y":59.49},{"x":26.4,"y":84.47},{"x":37.3,"y":39.13},{"x":13.9,"y":70.98},{"x":48.7,"y":49.16},{"x":23.6,"y":79.95},{"x":45.5,"y":40.07},{"x":45.8,"y":44.33},{"x":25.8,"y":69.14},{"x":28.2,"y":46.22},{"x":39.1,"y":100.8},{"x":40.6,"y":56.33},{"x":26.6,"y":33.01},{"x":12.8,"y":35.16},{"x":13.1,"y":38.76},{"x":36.9,"y":41.52},{"x":49.6,"y":21.82},{"x":18.5,"y":57.68},{"x":23.9,"y":43.15},{"x":23.7,"y":85.03},{"x":14.0,"y":22.97},{"x":8.8,"y":28.54},{"x":33.9,"y":211.52},{"x":8.9,"y":30.69},{"x":13.0,"y":45.56},{"x":9.2,"y":26.44},{"x":6.6,"y":28.88},{"x":12.0,"y":43.85},{"x":29.9,"y":139.79},{"x":3.3,"y":10.56},{"x":13.2,"y":112.08},{"x":8.7,"y":35.93},{"x":9.9,"y":29.11},{"x":32.6,"y":79.84},{"x":27.9,"y":27.31},{"x":28.0,"y":39.69},{"x":52.0,"y":134.39},{"x":28.1,"y":51.7},{"x":58.3,"y":203.35},{"x":40.2,"y":50.17},{"x":15.3,"y":86.38},{"x":22.4,"y":34.79},{"x":42.6,"y":58.47},{"x":39.0,"y":95.03},{"x":31.4,"y":45.0},{"x":35.6,"y":40.55},{"x":36.1,"y":37.9},{"x":31.1,"y":73.39},{"x":39.2,"y":31.65},{"x":43.9,"y":45.9},{"x":21.8,"y":86.62},{"x":41.4,"y":59.25},{"x":9.0,"y":40.0},{"x":5.3,"y":28.48},{"x":6.7,"y":42.09},{"x":15.7,"y":47.31},{"x":21.6,"y":25.81},{"x":19.4,"y":63.47},{"x":21.3,"y":35.42},{"x":30.0,"y":49.17},{"x":19.1,"y":179.58},{"x":16.6,"y":146.28},{"x":9.9,"y":91.88},{"x":13.9,"y":63.58},{"x":11.2,"y":75.53},{"x":18.1,"y":71.11},{"x":18.9,"y":61.17},{"x":14.7,"y":26.33},{"x":5.7,"y":18.59},{"x":19.8,"y":44.91},{"x":17.7,"y":30.72},{"x":27.3,"y":53.31},{"x":23.5,"y":23.5},{"x":3.8,"y":32.19},{"x":55.8,"y":73.42},{"x":22.5,"y":79.46},{"x":29.5,"y":73.02},{"x":46.3,"y":41.78},{"x":10.9,"y":48.02},{"x":28.1,"y":238.97},{"x":15.3,"y":73.5},{"x":36.7,"y":193.74},{"x":16.8,"y":51.51},{"x":30.2,"y":64.11},{"x":33.9,"y":186.33},{"x":42.0,"y":76.52},{"x":47.6,"y":35.29},{"x":48.3,"y":66.52},{"x":34.0,"y":55.73},{"x":26.3,"y":60.34},{"x":33.5,"y":41.56},{"x":47.0,"y":144.97},{"x":4.8,"y":36.44},{"x":11.1,"y":25.41},{"x":31.4,"y":66.82},{"x":9.1,"y":61.39},{"x":23.0,"y":52.44},{"x":10.0,"y":44.26},{"x":9.2,"y":86.12},{"x":18.5,"y":48.84},{"x":36.0,"y":200.5},{"x":9.5,"y":61.21},{"x":22.3,"y":112.09},{"x":14.9,"y":62.01},{"x":14.1,"y":29.78},{"x":28.5,"y":61.01},{"x":43.1,"y":100.87},{"x":13.7,"y":70.16},{"x":41.5,"y":92.27},{"x":29.6,"y":61.9},{"x":29.1,"y":86.27},{"x":43.3,"y":52.32},{"x":23.4,"y":76.05},{"x":35.8,"y":104.52},{"x":49.2,"y":33.71},{"x":57.3,"y":67.61},{"x":35.3,"y":83.87},{"x":23.8,"y":38.92},{"x":18.3,"y":42.28},{"x":35.7,"y":47.16},{"x":16.2,"y":28.41},{"x":28.9,"y":50.51},{"x":23.8,"y":37.77},{"x":25.4,"y":52.77},{"x":16.2,"y":74.91},{"x":22.5,"y":99.68},{"x":30.1,"y":50.52},{"x":24.4,"y":50.63},{"x":44.4,"y":121.11},{"x":42.3,"y":46.14},{"x":43.5,"y":52.45},{"x":18.5,"y":33.76},{"x":55.9,"y":56.71},{"x":12.3,"y":66.58},{"x":31.2,"y":69.81},{"x":22.6,"y":70.69},{"x":26.6,"y":186.93},{"x":32.1,"y":62.6},{"x":35.2,"y":47.9},{"x":16.7,"y":53.57},{"x":19.9,"y":58.56},{"x":11.5,"y":41.35},{"x":39.6,"y":59.8},{"x":36.8,"y":58.88},{"x":40.9,"y":104.95},{"x":36.6,"y":92.67},{"x":32.1,"y":51.18},{"x":17.7,"y":30.66},{"x":35.7,"y":85.52},{"x":41.0,"y":84.36},{"x":43.1,"y":202.62},{"x":6.0,"y":48.83},{"x":21.4,"y":82.3},{"x":17.0,"y":48.39},{"x":11.7,"y":60.31},{"x":20.0,"y":62.62},{"x":5.9,"y":81.04},{"x":9.4,"y":74.16},{"x":19.6,"y":69.2},{"x":13.8,"y":64.34},{"x":11.6,"y":72.93},{"x":40.0,"y":113.61},{"x":13.1,"y":77.71},{"x":8.5,"y":79.49},{"x":12.2,"y":59.93},{"x":30.7,"y":99.55},{"x":26.2,"y":58.87},{"x":23.4,"y":120.38},{"x":23.9,"y":97.13},{"x":13.5,"y":52.37},{"x":31.5,"y":93.91},{"x":45.8,"y":145.08},{"x":19.5,"y":61.48},{"x":48.6,"y":45.82},{"x":57.5,"y":154.22},{"x":15.7,"y":89.93},{"x":28.2,"y":83.71},{"x":10.2,"y":75.48},{"x":32.0,"y":171.17},{"x":38.5,"y":105.17},{"x":30.5,"y":60.57},{"x":24.3,"y":103.54},{"x":32.1,"y":141.11},{"x":31.4,"y":89.2},{"x":48.0,"y":54.32},{"x":19.2,"y":65.5},{"x":30.5,"y":204.97},{"x":28.5,"y":75.67},{"x":35.9,"y":115.08},{"x":45.5,"y":42.77},{"x":14.7,"y":70.72},{"x":16.6,"y":54.18},{"x":41.2,"y":91.54},{"x":29.8,"y":47.47},{"x":37.1,"y":36.48},{"x":53.3,"y":134.14},{"x":23.4,"y":44.09},{"x":47.4,"y":168.82},{"x":53.7,"y":281.43},{"x":32.6,"y":88.91},{"x":49.1,"y":37.69},{"x":20.2,"y":55.06},{"x":46.3,"y":208.46},{"x":28.8,"y":182.46},{"x":54.7,"y":96.71},{"x":16.8,"y":57.33},{"x":56.1,"y":149.81},{"x":31.6,"y":48.88},{"x":31.4,"y":44.06},{"x":41.1,"y":76.46},{"x":27.0,"y":33.72},{"x":19.4,"y":30.96},{"x":29.0,"y":41.52},{"x":33.8,"y":34.06},{"x":34.6,"y":38.96},{"x":10.4,"y":35.13},{"x":25.7,"y":29.3},{"x":37.9,"y":74.69},{"x":47.9,"y":117.1},{"x":27.2,"y":35.54},{"x":46.1,"y":30.75},{"x":18.1,"y":50.52},{"x":9.5,"y":13.83},{"x":14.1,"y":39.12},{"x":13.1,"y":34.83},{"x":9.4,"y":58.86},{"x":10.9,"y":38.12},{"x":11.8,"y":72.55},{"x":13.0,"y":44.88},{"x":10.0,"y":26.02},{"x":15.4,"y":42.03},{"x":17.5,"y":60.99},{"x":13.0,"y":45.21},{"x":43.4,"y":442.65},{"x":12.2,"y":38.76},{"x":13.3,"y":96.27},{"x":14.6,"y":47.59},{"x":29.6,"y":67.14},{"x":22.9,"y":66.54},{"x":16.5,"y":87.52},{"x":28.9,"y":88.24},{"x":7.6,"y":9.71},{"x":7.3,"y":45.45},{"x":52.5,"y":102.98},{"x":10.9,"y":26.44},{"x":11.2,"y":25.56},{"x":20.0,"y":19.63},{"x":38.5,"y":101.43},{"x":17.1,"y":47.78},{"x":25.9,"y":264.72},{"x":13.7,"y":38.17},{"x":15.0,"y":95.34},{"x":16.3,"y":59.83},{"x":38.7,"y":56.53},{"x":25.5,"y":61.15},{"x":32.6,"y":70.65},{"x":34.5,"y":56.56},{"x":44.5,"y":41.37},{"x":17.9,"y":65.52},{"x":23.8,"y":67.97},{"x":37.2,"y":75.4},{"x":31.9,"y":70.13},{"x":22.0,"y":68.3},{"x":51.2,"y":108.14},{"x":31.7,"y":29.49},{"x":55.5,"y":64.59},{"x":31.5,"y":128.38},{"x":28.9,"y":178.64},{"x":18.0,"y":60.66},{"x":31.0,"y":78.17},{"x":19.0,"y":71.48},{"x":29.9,"y":126.04},{"x":24.5,"y":99.06},{"x":19.1,"y":97.2},{"x":26.4,"y":64.77},{"x":39.3,"y":77.46},{"x":31.2,"y":87.44},{"x":23.9,"y":70.04},{"x":28.5,"y":65.98},{"x":25.9,"y":81.94},{"x":37.3,"y":81.55},{"x":45.0,"y":106.24},{"x":39.2,"y":96.72},{"x":51.7,"y":52.63},{"x":56.4,"y":119.17},{"x":33.0,"y":151.43},{"x":54.8,"y":187.03},{"x":33.6,"y":75.84},{"x":44.0,"y":161.6},{"x":57.8,"y":82.95},{"x":54.1,"y":447.8},{"x":39.6,"y":178.99},{"x":7.4,"y":29.5},{"x":19.4,"y":74.88},{"x":22.2,"y":43.74},{"x":18.7,"y":68.29},{"x":29.3,"y":56.71},{"x":29.2,"y":43.37},{"x":21.5,"y":50.4},{"x":25.2,"y":55.21},{"x":54.6,"y":26.02},{"x":24.1,"y":53.49},{"x":23.5,"y":70.88},{"x":20.6,"y":90.99},{"x":47.1,"y":110.34},{"x":47.6,"y":155.24},{"x":14.3,"y":74.04},{"x":26.3,"y":56.89},{"x":28.6,"y":82.67},{"x":11.6,"y":69.35},{"x":29.2,"y":49.1},{"x":17.5,"y":108.4},{"x":33.5,"y":243.99},{"x":39.7,"y":72.38},{"x":39.4,"y":55.67},{"x":41.1,"y":73.95},{"x":24.1,"y":41.8},{"x":32.9,"y":53.53},{"x":31.1,"y":35.71},{"x":21.2,"y":56.25},{"x":31.9,"y":124.42},{"x":34.8,"y":48.68},{"x":22.3,"y":105.26},{"x":33.3,"y":108.85},{"x":34.6,"y":57.06},{"x":24.3,"y":68.02},{"x":32.3,"y":114.12},{"x":13.0,"y":72.91},{"x":9.2,"y":61.43},{"x":20.0,"y":47.84},{"x":24.0,"y":34.65},{"x":17.6,"y":51.63},{"x":25.7,"y":80.17},{"x":18.9,"y":78.68},{"x":28.6,"y":96.92},{"x":30.3,"y":139.34},{"x":19.5,"y":56.67},{"x":23.0,"y":93.24},{"x":21.0,"y":88.57},{"x":31.1,"y":52.23},{"x":13.7,"y":15.48},{"x":33.5,"y":98.37},{"x":36.6,"y":21.98},{"x":55.3,"y":55.56},{"x":42.6,"y":75.32},{"x":29.0,"y":48.16},{"x":15.6,"y":20.9},{"x":20.7,"y":46.01},{"x":14.3,"y":52.0},{"x":29.6,"y":87.06},{"x":48.7,"y":256.55},{"x":16.6,"y":40.4},{"x":19.4,"y":36.9},{"x":42.1,"y":42.65},{"x":29.0,"y":47.23},{"x":22.0,"y":72.28},{"x":18.6,"y":92.11},{"x":43.4,"y":81.89},{"x":41.7,"y":48.21},{"x":32.5,"y":70.3},{"x":39.9,"y":67.0},{"x":44.4,"y":48.42},{"x":46.9,"y":158.81},{"x":40.3,"y":31.22},{"x":40.1,"y":52.56},{"x":33.3,"y":27.41},{"x":40.0,"y":77.04},{"x":30.2,"y":76.88},{"x":41.3,"y":41.65},{"x":21.4,"y":28.01},{"x":28.0,"y":58.46},{"x":18.9,"y":49.54},{"x":22.4,"y":56.81},{"x":13.1,"y":39.66},{"x":38.7,"y":87.95},{"x":26.3,"y":131.94},{"x":28.0,"y":42.3},{"x":38.0,"y":70.4},{"x":24.7,"y":49.43},{"x":31.5,"y":88.67},{"x":15.3,"y":30.28},{"x":41.3,"y":33.72},{"x":17.6,"y":65.67},{"x":30.9,"y":58.92},{"x":48.5,"y":144.7},{"x":13.6,"y":50.07},{"x":32.5,"y":65.48},{"x":21.4,"y":34.92},{"x":23.5,"y":68.95},{"x":14.7,"y":61.17},{"x":13.9,"y":45.01},{"x":10.9,"y":59.51},{"x":29.7,"y":109.46},{"x":15.0,"y":39.28},{"x":37.8,"y":53.61},{"x":23.3,"y":19.77},{"x":22.1,"y":23.35},{"x":26.0,"y":51.89},{"x":14.1,"y":45.73},{"x":24.0,"y":58.36},{"x":21.8,"y":82.32},{"x":23.4,"y":51.39},{"x":32.3,"y":65.68},{"x":25.4,"y":35.2},{"x":35.4,"y":191.4},{"x":17.8,"y":103.27},{"x":18.6,"y":80.06},{"x":16.5,"y":110.06},{"x":34.5,"y":77.56},{"x":23.1,"y":96.36},{"x":37.3,"y":76.54},{"x":26.7,"y":58.3},{"x":10.2,"y":51.09},{"x":23.3,"y":81.92},{"x":23.7,"y":34.85},{"x":8.5,"y":34.56},{"x":2.7,"y":35.1},{"x":12.4,"y":45.84},{"x":8.3,"y":37.34},{"x":9.0,"y":65.23},{"x":10.8,"y":146.51},{"x":50.5,"y":86.85},{"x":8.2,"y":45.48},{"x":56.6,"y":64.42},{"x":18.6,"y":76.58},{"x":28.6,"y":56.58},{"x":16.9,"y":73.24},{"x":20.3,"y":25.66},{"x":40.0,"y":177.54},{"x":14.9,"y":56.17},{"x":32.2,"y":66.26},{"x":23.9,"y":101.96},{"x":19.4,"y":70.52},{"x":30.5,"y":107.56},{"x":55.4,"y":30.7},{"x":40.3,"y":128.61},{"x":33.8,"y":90.85},{"x":49.9,"y":139.04},{"x":39.8,"y":101.41},{"x":28.5,"y":66.63},{"x":23.6,"y":101.87},{"x":10.2,"y":48.02},{"x":8.2,"y":43.48},{"x":43.8,"y":52.93},{"x":20.9,"y":55.16},{"x":10.2,"y":23.63},{"x":37.4,"y":46.62},{"x":30.8,"y":57.11},{"x":26.1,"y":65.6},{"x":31.5,"y":66.13},{"x":28.3,"y":87.6},{"x":38.5,"y":81.43},{"x":26.1,"y":99.63},{"x":32.4,"y":56.05},{"x":24.5,"y":61.94},{"x":44.0,"y":55.78},{"x":30.6,"y":60.85},{"x":36.6,"y":33.2},{"x":47.7,"y":63.44},{"x":50.6,"y":73.39},{"x":46.5,"y":100.28},{"x":15.9,"y":94.24},{"x":26.0,"y":27.98},{"x":41.3,"y":64.63},{"x":41.5,"y":80.58},{"x":29.9,"y":100.95},{"x":34.5,"y":112.87},{"x":20.9,"y":68.25},{"x":43.1,"y":79.54},{"x":46.5,"y":104.87},{"x":30.7,"y":56.43},{"x":22.6,"y":65.95},{"x":41.4,"y":58.58},{"x":55.1,"y":56.01},{"x":79.8,"y":334.87},{"x":7.7,"y":60.49},{"x":66.5,"y":205.79},{"x":71.6,"y":147.32},{"x":43.4,"y":93.28},{"x":63.3,"y":178.57},{"x":17.1,"y":65.18},{"x":62.3,"y":363.64},{"x":41.1,"y":74.72},{"x":29.7,"y":83.7},{"x":60.7,"y":2136.41},{"x":13.8,"y":59.19},{"x":13.6,"y":40.36},{"x":59.6,"y":31.76},{"x":36.6,"y":118.17},{"x":59.0,"y":25.27},{"x":28.3,"y":30.21},{"x":52.3,"y":146.87},{"x":60.8,"y":58.42},{"x":37.3,"y":35.0},{"x":40.5,"y":133.09},{"x":48.4,"y":105.12},{"x":36.3,"y":189.33},{"x":17.1,"y":48.42},{"x":41.9,"y":97.8},{"x":32.5,"y":130.76},{"x":39.8,"y":137.56},{"x":23.1,"y":144.32},{"x":51.1,"y":192.69},{"x":29.2,"y":118.39},{"x":43.6,"y":148.15},{"x":30.4,"y":51.3},{"x":25.4,"y":34.59},{"x":22.4,"y":74.1},{"x":41.9,"y":59.99},{"x":53.2,"y":110.82},{"x":34.7,"y":91.67},{"x":44.9,"y":96.45},{"x":76.7,"y":287.47},{"x":13.6,"y":97.04},{"x":32.0,"y":101.5},{"x":23.2,"y":32.87},{"x":34.0,"y":54.6},{"x":46.8,"y":61.85},{"x":34.5,"y":58.36},{"x":60.0,"y":27.45},{"x":48.1,"y":36.75},{"x":24.9,"y":51.37},{"x":26.4,"y":58.05},{"x":13.4,"y":55.06},{"x":39.4,"y":77.48},{"x":50.2,"y":92.85},{"x":57.7,"y":125.0},{"x":27.0,"y":136.12},{"x":42.4,"y":162.13},{"x":30.8,"y":88.95},{"x":36.4,"y":176.11},{"x":11.0,"y":80.03},{"x":32.3,"y":85.76},{"x":16.7,"y":91.14},{"x":16.4,"y":81.98},{"x":37.7,"y":127.88},{"x":73.1,"y":84.01},{"x":28.2,"y":89.95},{"x":30.6,"y":148.26}]},{"variable":"recent_migration_rate","label":"Recent Migration Rate","spearman":0.373,"r_squared":0.0989,"slope":4.5992,"intercept":23.7188,"n":4988,"significant":true,"description":"Areas with higher recent migration rate consistently show higher crime rates","scatterSample":[{"x":9.8,"y":50.95},{"x":7.5,"y":54.02},{"x":7.2,"y":78.29},{"x":9.2,"y":91.16},{"x":8.3,"y":141.61},{"x":7.5,"y":128.08},{"x":7.7,"y":56.0},{"x":7.8,"y":56.85},{"x":6.9,"y":55.76},{"x":9.3,"y":98.95},{"x":8.6,"y":70.63},{"x":12.1,"y":88.28},{"x":6.7,"y":41.98},{"x":11.4,"y":62.84},{"x":20.3,"y":69.49},{"x":6.8,"y":115.63},{"x":15.2,"y":59.49},{"x":8.5,"y":84.47},{"x":13.7,"y":39.13},{"x":5.8,"y":70.98},{"x":13.5,"y":49.16},{"x":11.1,"y":79.95},{"x":8.8,"y":40.07},{"x":8.9,"y":44.33},{"x":7.3,"y":69.14},{"x":12.4,"y":46.22},{"x":12.5,"y":100.8},{"x":11.2,"y":56.33},{"x":8.7,"y":33.01},{"x":9.0,"y":35.16},{"x":8.1,"y":38.76},{"x":15.5,"y":41.52},{"x":14.8,"y":21.82},{"x":4.3,"y":57.68},{"x":7.4,"y":43.15},{"x":10.1,"y":85.03},{"x":8.6,"y":22.97},{"x":7.6,"y":28.54},{"x":13.6,"y":211.52},{"x":5.6,"y":30.69},{"x":6.5,"y":45.56},{"x":6.0,"y":26.44},{"x":4.8,"y":28.88},{"x":14.5,"y":43.85},{"x":10.5,"y":139.79},{"x":5.8,"y":10.56},{"x":5.9,"y":112.08},{"x":7.2,"y":35.93},{"x":7.3,"y":29.11},{"x":20.6,"y":79.84},{"x":8.7,"y":27.31},{"x":9.3,"y":39.69},{"x":16.6,"y":134.39},{"x":10.1,"y":51.7},{"x":13.6,"y":203.35},{"x":13.3,"y":50.17},{"x":8.0,"y":86.38},{"x":7.0,"y":34.79},{"x":21.4,"y":58.47},{"x":15.3,"y":95.03},{"x":12.5,"y":45.0},{"x":9.8,"y":40.55},{"x":15.4,"y":37.9},{"x":7.0,"y":73.39},{"x":15.2,"y":31.65},{"x":19.6,"y":45.9},{"x":5.7,"y":86.62},{"x":19.0,"y":59.25},{"x":8.9,"y":40.0},{"x":6.5,"y":28.48},{"x":7.3,"y":42.09},{"x":9.7,"y":47.31},{"x":10.1,"y":25.81},{"x":6.8,"y":63.47},{"x":11.4,"y":35.42},{"x":13.8,"y":49.17},{"x":7.8,"y":179.58},{"x":7.1,"y":146.28},{"x":7.1,"y":91.88},{"x":6.5,"y":63.58},{"x":7.8,"y":75.53},{"x":7.6,"y":71.11},{"x":7.1,"y":61.17},{"x":6.7,"y":26.33},{"x":9.2,"y":18.59},{"x":10.4,"y":44.91},{"x":8.0,"y":30.72},{"x":9.4,"y":53.31},{"x":10.2,"y":23.5},{"x":5.9,"y":32.19},{"x":22.1,"y":73.42},{"x":14.6,"y":79.46},{"x":14.5,"y":73.02},{"x":18.2,"y":41.78},{"x":6.8,"y":48.02},{"x":20.0,"y":238.97},{"x":9.9,"y":73.5},{"x":22.6,"y":193.74},{"x":14.2,"y":51.51},{"x":11.7,"y":64.11},{"x":20.6,"y":186.33},{"x":21.2,"y":76.52},{"x":20.3,"y":35.29},{"x":16.7,"y":66.52},{"x":11.8,"y":55.73},{"x":10.3,"y":60.34},{"x":12.1,"y":41.56},{"x":12.1,"y":144.97},{"x":5.8,"y":36.44},{"x":8.4,"y":25.41},{"x":11.7,"y":66.82},{"x":3.6,"y":61.39},{"x":7.7,"y":52.44},{"x":7.4,"y":44.26},{"x":7.0,"y":86.12},{"x":8.5,"y":48.84},{"x":12.3,"y":200.5},{"x":7.9,"y":61.21},{"x":7.4,"y":112.09},{"x":7.3,"y":62.01},{"x":7.2,"y":29.78},{"x":7.8,"y":61.01},{"x":12.7,"y":100.87},{"x":7.5,"y":70.16},{"x":9.9,"y":92.27},{"x":8.1,"y":61.9},{"x":10.3,"y":86.27},{"x":15.5,"y":52.32},{"x":6.0,"y":76.05},{"x":9.9,"y":104.52},{"x":16.2,"y":33.71},{"x":22.7,"y":67.61},{"x":14.4,"y":83.87},{"x":8.6,"y":38.92},{"x":9.3,"y":42.28},{"x":13.1,"y":47.16},{"x":5.4,"y":28.41},{"x":7.6,"y":50.51},{"x":9.9,"y":37.77},{"x":6.1,"y":52.77},{"x":6.5,"y":74.91},{"x":6.2,"y":99.68},{"x":9.5,"y":50.52},{"x":7.1,"y":50.63},{"x":17.7,"y":121.11},{"x":8.8,"y":46.14},{"x":7.7,"y":52.45},{"x":8.8,"y":33.76},{"x":14.2,"y":56.71},{"x":5.9,"y":66.58},{"x":8.6,"y":69.81},{"x":9.1,"y":70.69},{"x":6.6,"y":186.93},{"x":9.4,"y":62.6},{"x":8.4,"y":47.9},{"x":6.7,"y":53.57},{"x":6.7,"y":58.56},{"x":6.9,"y":41.35},{"x":6.2,"y":59.8},{"x":6.3,"y":58.88},{"x":12.4,"y":104.95},{"x":9.4,"y":92.67},{"x":8.6,"y":51.18},{"x":7.9,"y":30.66},{"x":11.7,"y":85.52},{"x":7.6,"y":84.36},{"x":8.4,"y":202.62},{"x":9.2,"y":48.83},{"x":6.7,"y":82.3},{"x":11.1,"y":48.39},{"x":7.4,"y":60.31},{"x":9.1,"y":62.62},{"x":8.0,"y":81.04},{"x":6.0,"y":74.16},{"x":10.4,"y":69.2},{"x":9.0,"y":64.34},{"x":6.6,"y":72.93},{"x":9.5,"y":113.61},{"x":8.7,"y":77.71},{"x":4.6,"y":79.49},{"x":8.3,"y":59.93},{"x":16.4,"y":99.55},{"x":10.9,"y":58.87},{"x":16.8,"y":120.38},{"x":11.9,"y":97.13},{"x":5.9,"y":52.37},{"x":14.8,"y":93.91},{"x":33.5,"y":145.08},{"x":11.1,"y":61.48},{"x":9.5,"y":45.82},{"x":10.6,"y":154.22},{"x":10.7,"y":89.93},{"x":13.3,"y":83.71},{"x":8.7,"y":75.48},{"x":18.6,"y":171.17},{"x":16.3,"y":105.17},{"x":15.3,"y":60.57},{"x":13.2,"y":103.54},{"x":20.0,"y":141.11},{"x":16.2,"y":89.2},{"x":26.6,"y":54.32},{"x":14.3,"y":65.5},{"x":18.8,"y":204.97},{"x":16.4,"y":75.67},{"x":21.0,"y":115.08},{"x":25.0,"y":42.77},{"x":10.1,"y":70.72},{"x":11.3,"y":54.18},{"x":14.1,"y":91.54},{"x":11.7,"y":47.47},{"x":14.8,"y":36.48},{"x":24.2,"y":134.14},{"x":11.1,"y":44.09},{"x":18.6,"y":168.82},{"x":21.7,"y":281.43},{"x":9.7,"y":88.91},{"x":8.9,"y":37.69},{"x":13.3,"y":55.06},{"x":17.5,"y":208.46},{"x":11.4,"y":182.46},{"x":17.0,"y":96.71},{"x":6.1,"y":57.33},{"x":16.0,"y":149.81},{"x":11.4,"y":48.88},{"x":8.4,"y":44.06},{"x":13.8,"y":76.46},{"x":8.3,"y":33.72},{"x":8.4,"y":30.96},{"x":10.5,"y":41.52},{"x":8.1,"y":34.06},{"x":19.8,"y":38.96},{"x":8.4,"y":35.13},{"x":7.8,"y":29.3},{"x":9.7,"y":74.69},{"x":10.7,"y":117.1},{"x":10.3,"y":35.54},{"x":12.2,"y":30.75},{"x":8.5,"y":50.52},{"x":5.5,"y":13.83},{"x":6.6,"y":39.12},{"x":7.9,"y":34.83},{"x":6.5,"y":58.86},{"x":8.0,"y":38.12},{"x":7.2,"y":72.55},{"x":6.5,"y":44.88},{"x":5.2,"y":26.02},{"x":8.2,"y":42.03},{"x":8.0,"y":60.99},{"x":4.4,"y":45.21},{"x":19.7,"y":442.65},{"x":7.1,"y":38.76},{"x":8.1,"y":96.27},{"x":7.6,"y":47.59},{"x":9.9,"y":67.14},{"x":7.1,"y":66.54},{"x":10.8,"y":87.52},{"x":8.3,"y":88.24},{"x":5.7,"y":9.71},{"x":7.0,"y":45.45},{"x":12.0,"y":102.98},{"x":7.2,"y":26.44},{"x":6.3,"y":25.56},{"x":8.5,"y":19.63},{"x":9.9,"y":101.43},{"x":7.4,"y":47.78},{"x":9.1,"y":264.72},{"x":7.8,"y":38.17},{"x":7.5,"y":95.34},{"x":6.6,"y":59.83},{"x":11.9,"y":56.53},{"x":7.2,"y":61.15},{"x":11.3,"y":70.65},{"x":16.5,"y":56.56},{"x":10.9,"y":41.37},{"x":8.0,"y":65.52},{"x":9.9,"y":67.97},{"x":11.2,"y":75.4},{"x":10.9,"y":70.13},{"x":7.0,"y":68.3},{"x":20.3,"y":108.14},{"x":7.7,"y":29.49},{"x":16.9,"y":64.59},{"x":11.3,"y":128.38},{"x":11.0,"y":178.64},{"x":10.6,"y":60.66},{"x":20.5,"y":78.17},{"x":25.8,"y":71.48},{"x":16.0,"y":126.04},{"x":15.9,"y":99.06},{"x":10.2,"y":97.2},{"x":13.5,"y":64.77},{"x":24.6,"y":77.46},{"x":16.9,"y":87.44},{"x":16.1,"y":70.04},{"x":15.5,"y":65.98},{"x":16.9,"y":81.94},{"x":20.3,"y":81.55},{"x":17.6,"y":106.24},{"x":18.1,"y":96.72},{"x":19.9,"y":52.63},{"x":31.3,"y":119.17},{"x":16.4,"y":151.43},{"x":20.4,"y":187.03},{"x":19.0,"y":75.84},{"x":21.2,"y":161.6},{"x":25.9,"y":82.95},{"x":17.8,"y":447.8},{"x":21.6,"y":178.99},{"x":6.3,"y":29.5},{"x":7.6,"y":74.88},{"x":10.8,"y":43.74},{"x":9.2,"y":68.29},{"x":16.0,"y":56.71},{"x":17.1,"y":43.37},{"x":8.4,"y":50.4},{"x":10.9,"y":55.21},{"x":17.3,"y":26.02},{"x":10.3,"y":53.49},{"x":10.5,"y":70.88},{"x":25.7,"y":90.99},{"x":33.3,"y":110.34},{"x":27.4,"y":155.24},{"x":8.5,"y":74.04},{"x":23.2,"y":56.89},{"x":11.5,"y":82.67},{"x":9.8,"y":69.35},{"x":14.8,"y":49.1},{"x":12.5,"y":108.4},{"x":24.6,"y":243.99},{"x":16.7,"y":72.38},{"x":22.8,"y":55.67},{"x":19.6,"y":73.95},{"x":8.4,"y":41.8},{"x":15.9,"y":53.53},{"x":23.3,"y":35.71},{"x":9.8,"y":56.25},{"x":13.8,"y":124.42},{"x":22.4,"y":48.68},{"x":7.5,"y":105.26},{"x":12.4,"y":108.85},{"x":21.0,"y":57.06},{"x":9.0,"y":68.02},{"x":15.5,"y":114.12},{"x":4.7,"y":72.91},{"x":6.8,"y":61.43},{"x":13.0,"y":47.84},{"x":12.4,"y":34.65},{"x":10.5,"y":51.63},{"x":14.8,"y":80.17},{"x":10.2,"y":78.68},{"x":15.2,"y":96.92},{"x":10.6,"y":139.34},{"x":8.8,"y":56.67},{"x":11.8,"y":93.24},{"x":6.4,"y":88.57},{"x":15.6,"y":52.23},{"x":10.1,"y":15.48},{"x":9.4,"y":98.37},{"x":19.2,"y":21.98},{"x":17.6,"y":55.56},{"x":18.0,"y":75.32},{"x":9.8,"y":48.16},{"x":8.7,"y":20.9},{"x":7.8,"y":46.01},{"x":6.8,"y":52.0},{"x":9.6,"y":87.06},{"x":22.3,"y":256.55},{"x":12.2,"y":40.4},{"x":13.9,"y":36.9},{"x":11.4,"y":42.65},{"x":7.6,"y":47.23},{"x":8.7,"y":72.28},{"x":7.3,"y":92.11},{"x":9.1,"y":81.89},{"x":10.1,"y":48.21},{"x":10.8,"y":70.3},{"x":12.1,"y":67.0},{"x":10.1,"y":48.42},{"x":11.8,"y":158.81},{"x":9.2,"y":31.22},{"x":8.9,"y":52.56},{"x":6.8,"y":27.41},{"x":11.2,"y":77.04},{"x":8.4,"y":76.88},{"x":15.2,"y":41.65},{"x":10.2,"y":28.01},{"x":11.2,"y":58.46},{"x":8.5,"y":49.54},{"x":9.0,"y":56.81},{"x":6.6,"y":39.66},{"x":9.8,"y":87.95},{"x":8.4,"y":131.94},{"x":8.2,"y":42.3},{"x":6.1,"y":70.4},{"x":9.3,"y":49.43},{"x":10.3,"y":88.67},{"x":7.3,"y":30.28},{"x":11.6,"y":33.72},{"x":7.9,"y":65.67},{"x":7.6,"y":58.92},{"x":11.1,"y":144.7},{"x":9.6,"y":50.07},{"x":11.2,"y":65.48},{"x":12.3,"y":34.92},{"x":12.6,"y":68.95},{"x":10.2,"y":61.17},{"x":8.8,"y":45.01},{"x":7.4,"y":59.51},{"x":14.5,"y":109.46},{"x":10.5,"y":39.28},{"x":15.3,"y":53.61},{"x":39.3,"y":19.77},{"x":12.2,"y":23.35},{"x":13.8,"y":51.89},{"x":7.7,"y":45.73},{"x":13.7,"y":58.36},{"x":11.1,"y":82.32},{"x":15.7,"y":51.39},{"x":11.2,"y":65.68},{"x":12.0,"y":35.2},{"x":14.9,"y":191.4},{"x":15.0,"y":103.27},{"x":10.3,"y":80.06},{"x":11.8,"y":110.06},{"x":15.8,"y":77.56},{"x":14.2,"y":96.36},{"x":14.0,"y":76.54},{"x":12.2,"y":58.3},{"x":9.5,"y":51.09},{"x":13.1,"y":81.92},{"x":13.3,"y":34.85},{"x":5.2,"y":34.56},{"x":6.0,"y":35.1},{"x":8.9,"y":45.84},{"x":6.7,"y":37.34},{"x":8.0,"y":65.23},{"x":6.5,"y":146.51},{"x":23.7,"y":86.85},{"x":6.8,"y":45.48},{"x":16.2,"y":64.42},{"x":7.9,"y":76.58},{"x":10.0,"y":56.58},{"x":7.0,"y":73.24},{"x":7.7,"y":25.66},{"x":21.4,"y":177.54},{"x":8.8,"y":56.17},{"x":18.4,"y":66.26},{"x":13.5,"y":101.96},{"x":10.1,"y":70.52},{"x":17.4,"y":107.56},{"x":26.8,"y":30.7},{"x":18.2,"y":128.61},{"x":17.4,"y":90.85},{"x":24.6,"y":139.04},{"x":22.1,"y":101.41},{"x":9.2,"y":66.63},{"x":9.4,"y":101.87},{"x":6.5,"y":48.02},{"x":5.5,"y":43.48},{"x":14.4,"y":52.93},{"x":8.3,"y":55.16},{"x":7.5,"y":23.63},{"x":13.3,"y":46.62},{"x":12.7,"y":57.11},{"x":7.0,"y":65.6},{"x":10.7,"y":66.13},{"x":9.0,"y":87.6},{"x":11.2,"y":81.43},{"x":10.1,"y":99.63},{"x":10.8,"y":56.05},{"x":12.2,"y":61.94},{"x":29.8,"y":55.78},{"x":15.2,"y":60.85},{"x":20.7,"y":33.2},{"x":25.3,"y":63.44},{"x":20.1,"y":73.39},{"x":21.8,"y":100.28},{"x":10.5,"y":94.24},{"x":18.2,"y":27.98},{"x":26.2,"y":64.63},{"x":26.5,"y":80.58},{"x":14.1,"y":100.95},{"x":17.5,"y":112.87},{"x":13.5,"y":68.25},{"x":20.0,"y":79.54},{"x":22.5,"y":104.87},{"x":17.1,"y":56.43},{"x":11.2,"y":65.95},{"x":16.8,"y":58.58},{"x":26.2,"y":56.01},{"x":46.7,"y":334.87},{"x":5.5,"y":60.49},{"x":39.1,"y":205.79},{"x":29.1,"y":147.32},{"x":17.7,"y":93.28},{"x":24.6,"y":178.57},{"x":6.2,"y":65.18},{"x":25.4,"y":363.64},{"x":25.7,"y":74.72},{"x":21.0,"y":83.7},{"x":32.2,"y":2136.41},{"x":5.2,"y":59.19},{"x":8.5,"y":40.36},{"x":31.1,"y":31.76},{"x":26.7,"y":118.17},{"x":21.2,"y":25.27},{"x":13.9,"y":30.21},{"x":20.6,"y":146.87},{"x":29.7,"y":58.42},{"x":14.9,"y":35.0},{"x":15.8,"y":133.09},{"x":20.6,"y":105.12},{"x":15.7,"y":189.33},{"x":10.1,"y":48.42},{"x":19.0,"y":97.8},{"x":19.4,"y":130.76},{"x":20.0,"y":137.56},{"x":10.2,"y":144.32},{"x":37.9,"y":192.69},{"x":17.1,"y":118.39},{"x":21.0,"y":148.15},{"x":13.1,"y":51.3},{"x":8.2,"y":34.59},{"x":8.2,"y":74.1},{"x":17.3,"y":59.99},{"x":23.7,"y":110.82},{"x":11.4,"y":91.67},{"x":10.5,"y":96.45},{"x":29.6,"y":287.47},{"x":8.2,"y":97.04},{"x":18.9,"y":101.5},{"x":20.0,"y":32.87},{"x":8.2,"y":54.6},{"x":23.0,"y":61.85},{"x":39.3,"y":58.36},{"x":28.8,"y":27.45},{"x":22.1,"y":36.75},{"x":8.1,"y":51.37},{"x":7.2,"y":58.05},{"x":6.1,"y":55.06},{"x":11.0,"y":77.48},{"x":18.5,"y":92.85},{"x":20.8,"y":125.0},{"x":31.3,"y":136.12},{"x":28.8,"y":162.13},{"x":15.6,"y":88.95},{"x":22.8,"y":176.11},{"x":21.7,"y":80.03},{"x":13.7,"y":85.76},{"x":8.8,"y":91.14},{"x":9.3,"y":81.98},{"x":21.9,"y":127.88},{"x":44.8,"y":84.01},{"x":35.1,"y":89.95},{"x":15.7,"y":148.26}]},{"variable":"deprivation_score","label":"Deprivation Score","spearman":0.3677,"r_squared":0.005,"slope":1.3482,"intercept":64.9069,"n":4988,"significant":true,"description":"Areas with higher deprivation score consistently show higher crime rates","scatterSample":[{"x":13.4,"y":50.95},{"x":16.3,"y":54.02},{"x":25.1,"y":78.29},{"x":16.9,"y":91.16},{"x":21.5,"y":141.61},{"x":19.5,"y":128.08},{"x":23.9,"y":56.0},{"x":22.8,"y":56.85},{"x":22.0,"y":55.76},{"x":20.6,"y":98.95},{"x":21.5,"y":70.63},{"x":14.9,"y":88.28},{"x":25.5,"y":41.98},{"x":17.0,"y":62.84},{"x":11.0,"y":69.49},{"x":25.8,"y":115.63},{"x":14.5,"y":59.49},{"x":14.9,"y":84.47},{"x":8.9,"y":39.13},{"x":11.2,"y":70.98},{"x":12.3,"y":49.16},{"x":3.1,"y":79.95},{"x":14.6,"y":40.07},{"x":17.8,"y":44.33},{"x":9.7,"y":69.14},{"x":10.7,"y":46.22},{"x":17.6,"y":100.8},{"x":12.3,"y":56.33},{"x":10.9,"y":33.01},{"x":5.1,"y":35.16},{"x":12.7,"y":38.76},{"x":10.5,"y":41.52},{"x":15.6,"y":21.82},{"x":20.8,"y":57.68},{"x":12.1,"y":43.15},{"x":17.1,"y":85.03},{"x":12.6,"y":22.97},{"x":12.3,"y":28.54},{"x":10.8,"y":211.52},{"x":11.8,"y":30.69},{"x":14.2,"y":45.56},{"x":11.5,"y":26.44},{"x":18.1,"y":28.88},{"x":12.0,"y":43.85},{"x":16.1,"y":139.79},{"x":6.6,"y":10.56},{"x":18.8,"y":112.08},{"x":8.2,"y":35.93},{"x":11.5,"y":29.11},{"x":13.7,"y":79.84},{"x":19.1,"y":27.31},{"x":9.4,"y":39.69},{"x":14.9,"y":134.39},{"x":19.8,"y":51.7},{"x":22.4,"y":203.35},{"x":20.0,"y":50.17},{"x":18.2,"y":86.38},{"x":10.9,"y":34.79},{"x":9.5,"y":58.47},{"x":18.4,"y":95.03},{"x":14.8,"y":45.0},{"x":15.8,"y":40.55},{"x":10.5,"y":37.9},{"x":24.0,"y":73.39},{"x":18.6,"y":31.65},{"x":17.8,"y":45.9},{"x":24.5,"y":86.62},{"x":16.7,"y":59.25},{"x":4.1,"y":40.0},{"x":9.0,"y":28.48},{"x":12.7,"y":42.09},{"x":6.6,"y":47.31},{"x":12.2,"y":25.81},{"x":9.3,"y":63.47},{"x":9.3,"y":35.42},{"x":6.2,"y":49.17},{"x":15.8,"y":179.58},{"x":16.0,"y":146.28},{"x":20.8,"y":91.88},{"x":12.4,"y":63.58},{"x":9.7,"y":75.53},{"x":9.4,"y":71.11},{"x":8.1,"y":61.17},{"x":9.8,"y":26.33},{"x":7.8,"y":18.59},{"x":12.4,"y":44.91},{"x":7.9,"y":30.72},{"x":10.4,"y":53.31},{"x":8.0,"y":23.5},{"x":14.1,"y":32.19},{"x":10.0,"y":73.42},{"x":19.5,"y":79.46},{"x":12.8,"y":73.02},{"x":5.9,"y":41.78},{"x":25.2,"y":48.02},{"x":13.7,"y":238.97},{"x":19.3,"y":73.5},{"x":15.6,"y":193.74},{"x":21.3,"y":51.51},{"x":23.2,"y":64.11},{"x":14.6,"y":186.33},{"x":14.5,"y":76.52},{"x":5.9,"y":35.29},{"x":13.7,"y":66.52},{"x":16.8,"y":55.73},{"x":14.9,"y":60.34},{"x":13.4,"y":41.56},{"x":19.6,"y":144.97},{"x":11.8,"y":36.44},{"x":6.2,"y":25.41},{"x":12.9,"y":66.82},{"x":26.1,"y":61.39},{"x":14.6,"y":52.44},{"x":14.5,"y":44.26},{"x":21.5,"y":86.12},{"x":13.4,"y":48.84},{"x":15.8,"y":200.5},{"x":11.9,"y":61.21},{"x":22.8,"y":112.09},{"x":11.8,"y":62.01},{"x":10.4,"y":29.78},{"x":17.9,"y":61.01},{"x":15.4,"y":100.87},{"x":20.8,"y":70.16},{"x":15.0,"y":92.27},{"x":19.0,"y":61.9},{"x":13.1,"y":86.27},{"x":13.7,"y":52.32},{"x":22.2,"y":76.05},{"x":25.3,"y":104.52},{"x":6.7,"y":33.71},{"x":9.4,"y":67.61},{"x":8.7,"y":83.87},{"x":12.5,"y":38.92},{"x":17.9,"y":42.28},{"x":7.5,"y":47.16},{"x":21.9,"y":28.41},{"x":16.9,"y":50.51},{"x":8.4,"y":37.77},{"x":11.7,"y":52.77},{"x":19.8,"y":74.91},{"x":17.6,"y":99.68},{"x":23.6,"y":50.52},{"x":15.6,"y":50.63},{"x":12.7,"y":121.11},{"x":24.2,"y":46.14},{"x":22.0,"y":52.45},{"x":6.9,"y":33.76},{"x":16.5,"y":56.71},{"x":15.0,"y":66.58},{"x":21.3,"y":69.81},{"x":16.2,"y":70.69},{"x":24.4,"y":186.93},{"x":17.7,"y":62.6},{"x":18.1,"y":47.9},{"x":8.7,"y":53.57},{"x":23.5,"y":58.56},{"x":12.8,"y":41.35},{"x":20.5,"y":59.8},{"x":22.0,"y":58.88},{"x":16.9,"y":104.95},{"x":13.4,"y":92.67},{"x":8.4,"y":51.18},{"x":6.6,"y":30.66},{"x":11.2,"y":85.52},{"x":22.1,"y":84.36},{"x":21.2,"y":202.62},{"x":8.5,"y":48.83},{"x":19.4,"y":82.3},{"x":16.0,"y":48.39},{"x":15.6,"y":60.31},{"x":11.3,"y":62.62},{"x":9.7,"y":81.04},{"x":24.9,"y":74.16},{"x":18.7,"y":69.2},{"x":16.4,"y":64.34},{"x":13.6,"y":72.93},{"x":23.1,"y":113.61},{"x":10.8,"y":77.71},{"x":19.2,"y":79.49},{"x":22.2,"y":59.93},{"x":18.2,"y":99.55},{"x":19.3,"y":58.87},{"x":17.2,"y":120.38},{"x":18.6,"y":97.13},{"x":18.9,"y":52.37},{"x":16.4,"y":93.91},{"x":12.2,"y":145.08},{"x":11.8,"y":61.48},{"x":14.9,"y":45.82},{"x":19.0,"y":154.22},{"x":20.7,"y":89.93},{"x":7.3,"y":83.71},{"x":20.1,"y":75.48},{"x":18.3,"y":171.17},{"x":14.1,"y":105.17},{"x":9.9,"y":60.57},{"x":25.2,"y":103.54},{"x":17.7,"y":141.11},{"x":17.2,"y":89.2},{"x":11.8,"y":54.32},{"x":21.0,"y":65.5},{"x":18.3,"y":204.97},{"x":6.2,"y":75.67},{"x":20.3,"y":115.08},{"x":6.7,"y":42.77},{"x":26.7,"y":70.72},{"x":6.3,"y":54.18},{"x":19.9,"y":91.54},{"x":6.3,"y":47.47},{"x":8.6,"y":36.48},{"x":20.1,"y":134.14},{"x":10.9,"y":44.09},{"x":8.8,"y":168.82},{"x":21.6,"y":281.43},{"x":21.8,"y":88.91},{"x":14.3,"y":37.69},{"x":15.7,"y":55.06},{"x":19.1,"y":208.46},{"x":22.5,"y":182.46},{"x":17.7,"y":96.71},{"x":24.3,"y":57.33},{"x":18.9,"y":149.81},{"x":16.6,"y":48.88},{"x":17.1,"y":44.06},{"x":9.4,"y":76.46},{"x":15.6,"y":33.72},{"x":8.7,"y":30.96},{"x":15.9,"y":41.52},{"x":13.9,"y":34.06},{"x":11.6,"y":38.96},{"x":6.9,"y":35.13},{"x":13.5,"y":29.3},{"x":12.3,"y":74.69},{"x":16.8,"y":117.1},{"x":15.0,"y":35.54},{"x":16.0,"y":30.75},{"x":14.0,"y":50.52},{"x":12.4,"y":13.83},{"x":10.8,"y":39.12},{"x":12.7,"y":34.83},{"x":21.8,"y":58.86},{"x":15.7,"y":38.12},{"x":12.8,"y":72.55},{"x":18.2,"y":44.88},{"x":10.2,"y":26.02},{"x":13.2,"y":42.03},{"x":12.9,"y":60.99},{"x":15.9,"y":45.21},{"x":17.7,"y":442.65},{"x":16.8,"y":38.76},{"x":19.5,"y":96.27},{"x":9.7,"y":47.59},{"x":18.8,"y":67.14},{"x":18.9,"y":66.54},{"x":21.8,"y":87.52},{"x":18.4,"y":88.24},{"x":6.6,"y":9.71},{"x":16.2,"y":45.45},{"x":22.3,"y":102.98},{"x":8.2,"y":26.44},{"x":11.4,"y":25.56},{"x":6.6,"y":19.63},{"x":13.8,"y":101.43},{"x":12.5,"y":47.78},{"x":23.3,"y":264.72},{"x":9.1,"y":38.17},{"x":22.4,"y":95.34},{"x":13.0,"y":59.83},{"x":21.6,"y":56.53},{"x":17.2,"y":61.15},{"x":11.0,"y":70.65},{"x":8.3,"y":56.56},{"x":17.8,"y":41.37},{"x":20.6,"y":65.52},{"x":22.1,"y":67.97},{"x":14.9,"y":75.4},{"x":22.1,"y":70.13},{"x":23.2,"y":68.3},{"x":17.3,"y":108.14},{"x":12.9,"y":29.49},{"x":18.9,"y":64.59},{"x":19.3,"y":128.38},{"x":16.8,"y":178.64},{"x":24.9,"y":60.66},{"x":15.1,"y":78.17},{"x":19.7,"y":71.48},{"x":17.8,"y":126.04},{"x":23.3,"y":99.06},{"x":24.6,"y":97.2},{"x":12.5,"y":64.77},{"x":12.1,"y":77.46},{"x":13.9,"y":87.44},{"x":15.2,"y":70.04},{"x":8.2,"y":65.98},{"x":8.1,"y":81.94},{"x":16.2,"y":81.55},{"x":6.3,"y":106.24},{"x":9.0,"y":96.72},{"x":4.7,"y":52.63},{"x":8.7,"y":119.17},{"x":18.8,"y":151.43},{"x":3.9,"y":187.03},{"x":12.8,"y":75.84},{"x":6.2,"y":161.6},{"x":6.4,"y":82.95},{"x":9.3,"y":447.8},{"x":3.2,"y":178.99},{"x":8.9,"y":29.5},{"x":7.2,"y":74.88},{"x":13.7,"y":43.74},{"x":13.7,"y":68.29},{"x":15.9,"y":56.71},{"x":9.0,"y":43.37},{"x":12.2,"y":50.4},{"x":14.4,"y":55.21},{"x":8.6,"y":26.02},{"x":13.9,"y":53.49},{"x":7.0,"y":70.88},{"x":17.3,"y":90.99},{"x":6.7,"y":110.34},{"x":5.2,"y":155.24},{"x":21.7,"y":74.04},{"x":15.4,"y":56.89},{"x":19.8,"y":82.67},{"x":21.7,"y":69.35},{"x":11.3,"y":49.1},{"x":19.8,"y":108.4},{"x":13.9,"y":243.99},{"x":13.0,"y":72.38},{"x":12.4,"y":55.67},{"x":8.9,"y":73.95},{"x":12.1,"y":41.8},{"x":8.8,"y":53.53},{"x":7.7,"y":35.71},{"x":7.4,"y":56.25},{"x":19.1,"y":124.42},{"x":13.8,"y":48.68},{"x":21.8,"y":105.26},{"x":17.5,"y":108.85},{"x":10.0,"y":57.06},{"x":12.6,"y":68.02},{"x":15.5,"y":114.12},{"x":21.9,"y":72.91},{"x":21.5,"y":61.43},{"x":11.8,"y":47.84},{"x":9.9,"y":34.65},{"x":9.5,"y":51.63},{"x":17.6,"y":80.17},{"x":20.3,"y":78.68},{"x":14.0,"y":96.92},{"x":15.0,"y":139.34},{"x":13.9,"y":56.67},{"x":21.1,"y":93.24},{"x":25.0,"y":88.57},{"x":9.4,"y":52.23},{"x":10.0,"y":15.48},{"x":18.4,"y":98.37},{"x":5.7,"y":21.98},{"x":12.5,"y":55.56},{"x":7.8,"y":75.32},{"x":14.2,"y":48.16},{"x":9.3,"y":20.9},{"x":14.2,"y":46.01},{"x":17.0,"y":52.0},{"x":17.4,"y":87.06},{"x":8.4,"y":256.55},{"x":3.2,"y":40.4},{"x":2.3,"y":36.9},{"x":20.0,"y":42.65},{"x":15.4,"y":47.23},{"x":23.1,"y":72.28},{"x":23.2,"y":92.11},{"x":19.5,"y":81.89},{"x":23.3,"y":48.21},{"x":15.7,"y":70.3},{"x":17.3,"y":67.0},{"x":21.8,"y":48.42},{"x":21.7,"y":158.81},{"x":21.7,"y":31.22},{"x":23.7,"y":52.56},{"x":22.9,"y":27.41},{"x":21.1,"y":77.04},{"x":22.4,"y":76.88},{"x":17.0,"y":41.65},{"x":13.1,"y":28.01},{"x":17.6,"y":58.46},{"x":9.1,"y":49.54},{"x":6.7,"y":56.81},{"x":10.3,"y":39.66},{"x":22.5,"y":87.95},{"x":15.0,"y":131.94},{"x":14.5,"y":42.3},{"x":18.7,"y":70.4},{"x":17.8,"y":49.43},{"x":22.5,"y":88.67},{"x":10.4,"y":30.28},{"x":14.4,"y":33.72},{"x":10.0,"y":65.67},{"x":15.5,"y":58.92},{"x":19.6,"y":144.7},{"x":14.2,"y":50.07},{"x":5.0,"y":65.48},{"x":5.0,"y":34.92},{"x":11.1,"y":68.95},{"x":19.5,"y":61.17},{"x":5.6,"y":45.01},{"x":7.3,"y":59.51},{"x":7.1,"y":109.46},{"x":14.5,"y":39.28},{"x":6.4,"y":53.61},{"x":7.5,"y":19.77},{"x":7.4,"y":23.35},{"x":7.2,"y":51.89},{"x":8.4,"y":45.73},{"x":16.5,"y":58.36},{"x":15.5,"y":82.32},{"x":17.3,"y":51.39},{"x":8.5,"y":65.68},{"x":8.3,"y":35.2},{"x":17.6,"y":191.4},{"x":23.9,"y":103.27},{"x":17.9,"y":80.06},{"x":19.4,"y":110.06},{"x":12.6,"y":77.56},{"x":16.2,"y":96.36},{"x":16.9,"y":76.54},{"x":10.1,"y":58.3},{"x":23.8,"y":51.09},{"x":18.0,"y":81.92},{"x":6.7,"y":34.85},{"x":12.2,"y":34.56},{"x":8.8,"y":35.1},{"x":9.9,"y":45.84},{"x":16.5,"y":37.34},{"x":10.2,"y":65.23},{"x":19.1,"y":146.51},{"x":9.4,"y":86.85},{"x":13.8,"y":45.48},{"x":9.5,"y":64.42},{"x":12.3,"y":76.58},{"x":11.1,"y":56.58},{"x":20.6,"y":73.24},{"x":9.8,"y":25.66},{"x":15.7,"y":177.54},{"x":21.9,"y":56.17},{"x":14.1,"y":66.26},{"x":16.1,"y":101.96},{"x":26.2,"y":70.52},{"x":20.1,"y":107.56},{"x":6.4,"y":30.7},{"x":18.1,"y":128.61},{"x":20.8,"y":90.85},{"x":16.8,"y":139.04},{"x":18.1,"y":101.41},{"x":21.3,"y":66.63},{"x":14.3,"y":101.87},{"x":12.4,"y":48.02},{"x":9.9,"y":43.48},{"x":13.4,"y":52.93},{"x":14.3,"y":55.16},{"x":8.1,"y":23.63},{"x":17.8,"y":46.62},{"x":19.0,"y":57.11},{"x":16.9,"y":65.6},{"x":21.2,"y":66.13},{"x":20.3,"y":87.6},{"x":15.8,"y":81.43},{"x":17.0,"y":99.63},{"x":12.5,"y":56.05},{"x":16.9,"y":61.94},{"x":6.1,"y":55.78},{"x":14.7,"y":60.85},{"x":8.5,"y":33.2},{"x":6.2,"y":63.44},{"x":12.1,"y":73.39},{"x":11.8,"y":100.28},{"x":24.3,"y":94.24},{"x":5.8,"y":27.98},{"x":4.9,"y":64.63},{"x":11.0,"y":80.58},{"x":16.6,"y":100.95},{"x":10.7,"y":112.87},{"x":15.1,"y":68.25},{"x":5.7,"y":79.54},{"x":15.9,"y":104.87},{"x":7.3,"y":56.43},{"x":18.8,"y":65.95},{"x":9.9,"y":58.58},{"x":7.4,"y":56.01},{"x":12.0,"y":334.87},{"x":29.3,"y":60.49},{"x":10.3,"y":205.79},{"x":9.2,"y":147.32},{"x":7.5,"y":93.28},{"x":3.6,"y":178.57},{"x":25.7,"y":65.18},{"x":5.3,"y":363.64},{"x":9.1,"y":74.72},{"x":16.6,"y":83.7},{"x":10.7,"y":2136.41},{"x":13.9,"y":59.19},{"x":12.3,"y":40.36},{"x":2.7,"y":31.76},{"x":15.1,"y":118.17},{"x":6.2,"y":25.27},{"x":9.1,"y":30.21},{"x":11.4,"y":146.87},{"x":7.9,"y":58.42},{"x":11.2,"y":35.0},{"x":22.7,"y":133.09},{"x":7.0,"y":105.12},{"x":12.5,"y":189.33},{"x":17.7,"y":48.42},{"x":19.7,"y":97.8},{"x":12.5,"y":130.76},{"x":9.4,"y":137.56},{"x":10.3,"y":144.32},{"x":7.5,"y":192.69},{"x":15.9,"y":118.39},{"x":18.4,"y":148.15},{"x":19.9,"y":51.3},{"x":14.1,"y":34.59},{"x":21.6,"y":74.1},{"x":13.2,"y":59.99},{"x":13.3,"y":110.82},{"x":16.0,"y":91.67},{"x":18.6,"y":96.45},{"x":9.6,"y":287.47},{"x":20.8,"y":97.04},{"x":10.4,"y":101.5},{"x":7.4,"y":32.87},{"x":17.0,"y":54.6},{"x":10.5,"y":61.85},{"x":4.9,"y":58.36},{"x":3.3,"y":27.45},{"x":9.0,"y":36.75},{"x":17.1,"y":51.37},{"x":21.5,"y":58.05},{"x":25.3,"y":55.06},{"x":17.8,"y":77.48},{"x":15.2,"y":92.85},{"x":16.8,"y":125.0},{"x":15.4,"y":136.12},{"x":11.9,"y":162.13},{"x":15.3,"y":88.95},{"x":10.1,"y":176.11},{"x":6.6,"y":80.03},{"x":20.1,"y":85.76},{"x":20.6,"y":91.14},{"x":28.9,"y":81.98},{"x":18.0,"y":127.88},{"x":8.0,"y":84.01},{"x":19.5,"y":89.95},{"x":14.9,"y":148.26}]},{"variable":"population_density","label":"Population Density","spearman":0.2144,"r_squared":0.0001,"slope":-0.0001,"intercept":85.9421,"n":4988,"significant":false,"description":"Areas with higher population density weakly show higher crime rates","scatterSample":[{"x":12585.3,"y":50.95},{"x":9310.9,"y":54.02},{"x":1412.0,"y":78.29},{"x":3510.9,"y":91.16},{"x":5776.1,"y":141.61},{"x":6986.9,"y":128.08},{"x":8484.6,"y":56.0},{"x":10712.5,"y":56.85},{"x":10667.0,"y":55.76},{"x":6157.2,"y":98.95},{"x":7057.0,"y":70.63},{"x":7102.7,"y":88.28},{"x":3924.0,"y":41.98},{"x":6013.1,"y":62.84},{"x":13422.5,"y":69.49},{"x":12102.7,"y":115.63},{"x":8387.6,"y":59.49},{"x":6428.3,"y":84.47},{"x":12475.6,"y":39.13},{"x":494.8,"y":70.98},{"x":6682.3,"y":49.16},{"x":1136.1,"y":79.95},{"x":9808.0,"y":40.07},{"x":10542.1,"y":44.33},{"x":7321.5,"y":69.14},{"x":5790.2,"y":46.22},{"x":10143.5,"y":100.8},{"x":2653.4,"y":56.33},{"x":6131.0,"y":33.01},{"x":270.7,"y":35.16},{"x":4587.5,"y":38.76},{"x":6127.6,"y":41.52},{"x":13444.7,"y":21.82},{"x":3361.0,"y":57.68},{"x":6746.5,"y":43.15},{"x":6596.7,"y":85.03},{"x":6965.3,"y":22.97},{"x":5156.7,"y":28.54},{"x":4343.9,"y":211.52},{"x":6490.0,"y":30.69},{"x":5280.7,"y":45.56},{"x":2854.7,"y":26.44},{"x":6816.4,"y":28.88},{"x":4323.7,"y":43.85},{"x":9147.5,"y":139.79},{"x":4906.0,"y":10.56},{"x":8504.6,"y":112.08},{"x":1190.1,"y":35.93},{"x":7023.3,"y":29.11},{"x":4436.3,"y":79.84},{"x":12372.4,"y":27.31},{"x":5659.6,"y":39.69},{"x":13414.1,"y":134.39},{"x":12646.3,"y":51.7},{"x":9500.0,"y":203.35},{"x":2746.6,"y":50.17},{"x":15512.6,"y":86.38},{"x":5559.1,"y":34.79},{"x":16362.8,"y":58.47},{"x":7991.9,"y":95.03},{"x":6792.8,"y":45.0},{"x":6400.3,"y":40.55},{"x":14980.1,"y":37.9},{"x":9296.9,"y":73.39},{"x":13205.9,"y":31.65},{"x":8367.8,"y":45.9},{"x":7459.0,"y":86.62},{"x":12196.2,"y":59.25},{"x":1858.0,"y":40.0},{"x":1225.6,"y":28.48},{"x":2099.2,"y":42.09},{"x":3497.4,"y":47.31},{"x":6547.6,"y":25.81},{"x":4737.6,"y":63.47},{"x":10762.3,"y":35.42},{"x":4346.0,"y":49.17},{"x":6063.0,"y":179.58},{"x":592.1,"y":146.28},{"x":3813.1,"y":91.88},{"x":204.1,"y":63.58},{"x":1685.6,"y":75.53},{"x":778.5,"y":71.11},{"x":3971.5,"y":61.17},{"x":6950.9,"y":26.33},{"x":3345.5,"y":18.59},{"x":9983.8,"y":44.91},{"x":4578.0,"y":30.72},{"x":7354.7,"y":53.31},{"x":4195.2,"y":23.5},{"x":1870.1,"y":32.19},{"x":17529.0,"y":73.42},{"x":5441.7,"y":79.46},{"x":5411.5,"y":73.02},{"x":6931.8,"y":41.78},{"x":15089.5,"y":48.02},{"x":9302.1,"y":238.97},{"x":13834.0,"y":73.5},{"x":12586.6,"y":193.74},{"x":18055.6,"y":51.51},{"x":17370.8,"y":64.11},{"x":3169.2,"y":186.33},{"x":11311.1,"y":76.52},{"x":12442.2,"y":35.29},{"x":12374.7,"y":66.52},{"x":11049.9,"y":55.73},{"x":9060.4,"y":60.34},{"x":10166.5,"y":41.56},{"x":14695.2,"y":144.97},{"x":1485.7,"y":36.44},{"x":3624.6,"y":25.41},{"x":8857.4,"y":66.82},{"x":9060.6,"y":61.39},{"x":3573.6,"y":52.44},{"x":3376.2,"y":44.26},{"x":5330.3,"y":86.12},{"x":10776.6,"y":48.84},{"x":5417.2,"y":200.5},{"x":3487.2,"y":61.21},{"x":8302.9,"y":112.09},{"x":4236.4,"y":62.01},{"x":4283.8,"y":29.78},{"x":8645.5,"y":61.01},{"x":11981.4,"y":100.87},{"x":5847.3,"y":70.16},{"x":7536.9,"y":92.27},{"x":14532.8,"y":61.9},{"x":10420.2,"y":86.27},{"x":4598.0,"y":52.32},{"x":10534.0,"y":76.05},{"x":11828.6,"y":104.52},{"x":6604.1,"y":33.71},{"x":6465.0,"y":67.61},{"x":19629.6,"y":83.87},{"x":8330.9,"y":38.92},{"x":6000.0,"y":42.28},{"x":4307.0,"y":47.16},{"x":10771.8,"y":28.41},{"x":10633.7,"y":50.51},{"x":11736.9,"y":37.77},{"x":5558.2,"y":52.77},{"x":7658.2,"y":74.91},{"x":6817.7,"y":99.68},{"x":7268.1,"y":50.52},{"x":9707.3,"y":50.63},{"x":7600.7,"y":121.11},{"x":14737.6,"y":46.14},{"x":19883.4,"y":52.45},{"x":7259.8,"y":33.76},{"x":13441.5,"y":56.71},{"x":6402.8,"y":66.58},{"x":10779.0,"y":69.81},{"x":2806.9,"y":70.69},{"x":1293.1,"y":186.93},{"x":9887.5,"y":62.6},{"x":10282.2,"y":47.9},{"x":6117.6,"y":53.57},{"x":6519.6,"y":58.56},{"x":1894.1,"y":41.35},{"x":10895.2,"y":59.8},{"x":13276.9,"y":58.88},{"x":7321.9,"y":104.95},{"x":11946.5,"y":92.67},{"x":8854.8,"y":51.18},{"x":6298.2,"y":30.66},{"x":7361.9,"y":85.52},{"x":7356.0,"y":84.36},{"x":13836.4,"y":202.62},{"x":2098.0,"y":48.83},{"x":9554.7,"y":82.3},{"x":6657.3,"y":48.39},{"x":6007.0,"y":60.31},{"x":6530.4,"y":62.62},{"x":1691.2,"y":81.04},{"x":6622.0,"y":74.16},{"x":16248.8,"y":69.2},{"x":8808.8,"y":64.34},{"x":4286.1,"y":72.93},{"x":13770.8,"y":113.61},{"x":1580.9,"y":77.71},{"x":11437.0,"y":79.49},{"x":17511.8,"y":59.93},{"x":22266.5,"y":99.55},{"x":26185.8,"y":58.87},{"x":11769.1,"y":120.38},{"x":19269.2,"y":97.13},{"x":31763.5,"y":52.37},{"x":15184.1,"y":93.91},{"x":17086.3,"y":145.08},{"x":18335.1,"y":61.48},{"x":14207.5,"y":45.82},{"x":12866.1,"y":154.22},{"x":16391.5,"y":89.93},{"x":15734.8,"y":83.71},{"x":26342.5,"y":75.48},{"x":12601.7,"y":171.17},{"x":19891.2,"y":105.17},{"x":13558.6,"y":60.57},{"x":10864.4,"y":103.54},{"x":22304.8,"y":141.11},{"x":18983.5,"y":89.2},{"x":22823.7,"y":54.32},{"x":10947.5,"y":65.5},{"x":8792.5,"y":204.97},{"x":15791.3,"y":75.67},{"x":18848.0,"y":115.08},{"x":18320.9,"y":42.77},{"x":37912.1,"y":70.72},{"x":8508.8,"y":54.18},{"x":18021.2,"y":91.54},{"x":8618.5,"y":47.47},{"x":5317.5,"y":36.48},{"x":11523.2,"y":134.14},{"x":11257.2,"y":44.09},{"x":10607.2,"y":168.82},{"x":13340.5,"y":281.43},{"x":14685.5,"y":88.91},{"x":18273.6,"y":37.69},{"x":6658.1,"y":55.06},{"x":7548.8,"y":208.46},{"x":16080.8,"y":182.46},{"x":16722.0,"y":96.71},{"x":9175.3,"y":57.33},{"x":15835.2,"y":149.81},{"x":772.9,"y":48.88},{"x":10672.6,"y":44.06},{"x":1199.7,"y":76.46},{"x":9021.0,"y":33.72},{"x":3482.1,"y":30.96},{"x":10530.1,"y":41.52},{"x":9063.3,"y":34.06},{"x":5711.5,"y":38.96},{"x":1251.8,"y":35.13},{"x":9202.8,"y":29.3},{"x":6841.9,"y":74.69},{"x":6584.8,"y":117.1},{"x":5368.5,"y":35.54},{"x":14690.8,"y":30.75},{"x":3392.3,"y":50.52},{"x":5431.1,"y":13.83},{"x":2927.6,"y":39.12},{"x":5421.7,"y":34.83},{"x":7491.2,"y":58.86},{"x":4906.5,"y":38.12},{"x":6020.3,"y":72.55},{"x":2024.4,"y":44.88},{"x":7366.1,"y":26.02},{"x":4625.8,"y":42.03},{"x":5785.8,"y":60.99},{"x":3299.0,"y":45.21},{"x":5782.4,"y":442.65},{"x":5479.6,"y":38.76},{"x":7364.6,"y":96.27},{"x":3431.0,"y":47.59},{"x":6531.7,"y":67.14},{"x":8190.0,"y":66.54},{"x":5267.6,"y":87.52},{"x":8086.9,"y":88.24},{"x":4773.6,"y":9.71},{"x":897.1,"y":45.45},{"x":5638.5,"y":102.98},{"x":1477.2,"y":26.44},{"x":4344.5,"y":25.56},{"x":2623.9,"y":19.63},{"x":6705.2,"y":101.43},{"x":677.6,"y":47.78},{"x":2516.2,"y":264.72},{"x":2497.4,"y":38.17},{"x":5397.4,"y":95.34},{"x":1654.3,"y":59.83},{"x":9549.2,"y":56.53},{"x":6146.8,"y":61.15},{"x":8349.3,"y":70.65},{"x":4676.4,"y":56.56},{"x":4287.0,"y":41.37},{"x":8345.0,"y":65.52},{"x":7172.5,"y":67.97},{"x":3561.6,"y":75.4},{"x":9586.7,"y":70.13},{"x":5226.2,"y":68.3},{"x":13191.2,"y":108.14},{"x":8865.5,"y":29.49},{"x":10249.2,"y":64.59},{"x":6023.5,"y":128.38},{"x":7846.1,"y":178.64},{"x":23751.8,"y":60.66},{"x":27220.9,"y":78.17},{"x":19636.9,"y":71.48},{"x":17048.4,"y":126.04},{"x":13326.0,"y":99.06},{"x":14407.9,"y":97.2},{"x":17971.2,"y":64.77},{"x":11700.0,"y":77.46},{"x":12898.9,"y":87.44},{"x":21506.3,"y":70.04},{"x":13814.5,"y":65.98},{"x":14274.4,"y":81.94},{"x":14580.8,"y":81.55},{"x":8556.9,"y":106.24},{"x":12372.5,"y":96.72},{"x":16101.7,"y":52.63},{"x":19293.6,"y":119.17},{"x":18356.9,"y":151.43},{"x":11069.5,"y":187.03},{"x":13679.1,"y":75.84},{"x":12757.1,"y":161.6},{"x":17598.9,"y":82.95},{"x":8871.2,"y":447.8},{"x":10637.4,"y":178.99},{"x":3428.8,"y":29.5},{"x":2825.7,"y":74.88},{"x":6287.2,"y":43.74},{"x":420.2,"y":68.29},{"x":6939.2,"y":56.71},{"x":3930.6,"y":43.37},{"x":5023.6,"y":50.4},{"x":5272.7,"y":55.21},{"x":9488.3,"y":26.02},{"x":6277.2,"y":53.49},{"x":6707.6,"y":70.88},{"x":13395.5,"y":90.99},{"x":10305.2,"y":110.34},{"x":11043.8,"y":155.24},{"x":15757.8,"y":74.04},{"x":17705.1,"y":56.89},{"x":5472.7,"y":82.67},{"x":21971.8,"y":69.35},{"x":10680.4,"y":49.1},{"x":31294.3,"y":108.4},{"x":10271.1,"y":243.99},{"x":10917.9,"y":72.38},{"x":18477.2,"y":55.67},{"x":11748.6,"y":73.95},{"x":10888.7,"y":41.8},{"x":6611.4,"y":53.53},{"x":13086.2,"y":35.71},{"x":8844.2,"y":56.25},{"x":15177.0,"y":124.42},{"x":21931.8,"y":48.68},{"x":5357.8,"y":105.26},{"x":13265.9,"y":108.85},{"x":9160.4,"y":57.06},{"x":8600.3,"y":68.02},{"x":8970.5,"y":114.12},{"x":5583.3,"y":72.91},{"x":22053.1,"y":61.43},{"x":8440.3,"y":47.84},{"x":5837.5,"y":34.65},{"x":8614.9,"y":51.63},{"x":12649.5,"y":80.17},{"x":12569.7,"y":78.68},{"x":9931.3,"y":96.92},{"x":8490.4,"y":139.34},{"x":9313.3,"y":56.67},{"x":14416.8,"y":93.24},{"x":12246.3,"y":88.57},{"x":4004.4,"y":52.23},{"x":4429.2,"y":15.48},{"x":972.5,"y":98.37},{"x":10985.6,"y":21.98},{"x":21011.7,"y":55.56},{"x":6544.9,"y":75.32},{"x":9746.2,"y":48.16},{"x":7760.3,"y":20.9},{"x":10653.6,"y":46.01},{"x":9432.1,"y":52.0},{"x":3996.0,"y":87.06},{"x":6715.6,"y":256.55},{"x":2113.2,"y":40.4},{"x":2251.6,"y":36.9},{"x":11171.4,"y":42.65},{"x":17481.0,"y":47.23},{"x":13418.1,"y":72.28},{"x":14003.0,"y":92.11},{"x":16080.6,"y":81.89},{"x":16931.5,"y":48.21},{"x":14088.2,"y":70.3},{"x":15009.4,"y":67.0},{"x":21532.7,"y":48.42},{"x":18596.5,"y":158.81},{"x":20203.5,"y":31.22},{"x":20939.6,"y":52.56},{"x":24430.8,"y":27.41},{"x":15075.6,"y":77.04},{"x":6449.8,"y":76.88},{"x":17713.7,"y":41.65},{"x":7679.2,"y":28.01},{"x":9184.3,"y":58.46},{"x":4731.9,"y":49.54},{"x":8716.9,"y":56.81},{"x":6118.0,"y":39.66},{"x":13736.0,"y":87.95},{"x":6341.3,"y":131.94},{"x":8750.6,"y":42.3},{"x":14223.4,"y":70.4},{"x":11639.1,"y":49.43},{"x":10394.3,"y":88.67},{"x":2186.9,"y":30.28},{"x":11432.7,"y":33.72},{"x":2887.9,"y":65.67},{"x":11916.0,"y":58.92},{"x":12019.1,"y":144.7},{"x":1751.0,"y":50.07},{"x":1906.2,"y":65.48},{"x":13938.1,"y":34.92},{"x":484.4,"y":68.95},{"x":1642.1,"y":61.17},{"x":4542.7,"y":45.01},{"x":5113.6,"y":59.51},{"x":10078.3,"y":109.46},{"x":6825.0,"y":39.28},{"x":4969.9,"y":53.61},{"x":5344.8,"y":19.77},{"x":7742.2,"y":23.35},{"x":8859.7,"y":51.89},{"x":6213.6,"y":45.73},{"x":16914.8,"y":58.36},{"x":13056.1,"y":82.32},{"x":23784.1,"y":51.39},{"x":6545.8,"y":65.68},{"x":10604.3,"y":35.2},{"x":18634.3,"y":191.4},{"x":8791.6,"y":103.27},{"x":21401.9,"y":80.06},{"x":15143.2,"y":110.06},{"x":3155.0,"y":77.56},{"x":20141.7,"y":96.36},{"x":13654.8,"y":76.54},{"x":10568.7,"y":58.3},{"x":6759.8,"y":51.09},{"x":11849.8,"y":81.92},{"x":9498.5,"y":34.85},{"x":7905.5,"y":34.56},{"x":3426.9,"y":35.1},{"x":4349.2,"y":45.84},{"x":2577.4,"y":37.34},{"x":5633.3,"y":65.23},{"x":8466.9,"y":146.51},{"x":11031.5,"y":86.85},{"x":5518.0,"y":45.48},{"x":9706.6,"y":64.42},{"x":7095.5,"y":76.58},{"x":9177.4,"y":56.58},{"x":8325.5,"y":73.24},{"x":7662.3,"y":25.66},{"x":17186.3,"y":177.54},{"x":24000.0,"y":56.17},{"x":15342.8,"y":66.26},{"x":23430.3,"y":101.96},{"x":13415.8,"y":70.52},{"x":23700.7,"y":107.56},{"x":25085.6,"y":30.7},{"x":19268.3,"y":128.61},{"x":17359.4,"y":90.85},{"x":22004.4,"y":139.04},{"x":22998.6,"y":101.41},{"x":16994.0,"y":66.63},{"x":5818.0,"y":101.87},{"x":3776.4,"y":48.02},{"x":5902.7,"y":43.48},{"x":17928.6,"y":52.93},{"x":8518.7,"y":55.16},{"x":5432.2,"y":23.63},{"x":17924.5,"y":46.62},{"x":14100.2,"y":57.11},{"x":6246.6,"y":65.6},{"x":16512.2,"y":66.13},{"x":6666.7,"y":87.6},{"x":17379.5,"y":81.43},{"x":8190.1,"y":99.63},{"x":17509.3,"y":56.05},{"x":13126.4,"y":61.94},{"x":21812.4,"y":55.78},{"x":7527.6,"y":60.85},{"x":14916.0,"y":33.2},{"x":14273.9,"y":63.44},{"x":14920.8,"y":73.39},{"x":17133.2,"y":100.28},{"x":24242.8,"y":94.24},{"x":14965.9,"y":27.98},{"x":8842.1,"y":64.63},{"x":4905.8,"y":80.58},{"x":1001.3,"y":100.95},{"x":11339.5,"y":112.87},{"x":17578.3,"y":68.25},{"x":11908.9,"y":79.54},{"x":13305.6,"y":104.87},{"x":3854.3,"y":56.43},{"x":15470.5,"y":65.95},{"x":7569.8,"y":58.58},{"x":10850.9,"y":56.01},{"x":14975.4,"y":334.87},{"x":32623.3,"y":60.49},{"x":13693.8,"y":205.79},{"x":14384.8,"y":147.32},{"x":9595.8,"y":93.28},{"x":7561.8,"y":178.57},{"x":33354.0,"y":65.18},{"x":2967.0,"y":363.64},{"x":26937.9,"y":74.72},{"x":37938.7,"y":83.7},{"x":6866.5,"y":2136.41},{"x":3854.2,"y":59.19},{"x":4945.9,"y":40.36},{"x":27277.2,"y":31.76},{"x":7266.9,"y":118.17},{"x":34405.8,"y":25.27},{"x":34560.4,"y":30.21},{"x":25686.5,"y":146.87},{"x":7742.3,"y":58.42},{"x":17957.1,"y":35.0},{"x":11335.6,"y":133.09},{"x":10854.2,"y":105.12},{"x":9130.1,"y":189.33},{"x":19772.0,"y":48.42},{"x":21574.9,"y":97.8},{"x":5055.4,"y":130.76},{"x":6424.9,"y":137.56},{"x":2919.5,"y":144.32},{"x":8309.5,"y":192.69},{"x":10543.9,"y":118.39},{"x":5780.5,"y":148.15},{"x":12316.6,"y":51.3},{"x":16659.6,"y":34.59},{"x":10209.1,"y":74.1},{"x":35694.8,"y":59.99},{"x":16813.7,"y":110.82},{"x":11795.5,"y":91.67},{"x":13604.8,"y":96.45},{"x":10489.7,"y":287.47},{"x":8668.2,"y":97.04},{"x":13962.1,"y":101.5},{"x":32794.4,"y":32.87},{"x":20641.9,"y":54.6},{"x":15835.1,"y":61.85},{"x":11643.0,"y":58.36},{"x":21029.6,"y":27.45},{"x":22839.3,"y":36.75},{"x":12167.2,"y":51.37},{"x":10714.3,"y":58.05},{"x":20457.0,"y":55.06},{"x":7373.4,"y":77.48},{"x":15831.3,"y":92.85},{"x":11747.9,"y":125.0},{"x":2197.3,"y":136.12},{"x":11657.3,"y":162.13},{"x":13263.6,"y":88.95},{"x":17119.4,"y":176.11},{"x":13706.1,"y":80.03},{"x":11473.0,"y":85.76},{"x":15705.7,"y":91.14},{"x":28716.0,"y":81.98},{"x":21674.8,"y":127.88},{"x":17162.8,"y":84.01},{"x":17883.6,"y":89.95},{"x":10728.4,"y":148.26}]},{"variable":"no_qualifications_rate","label":"No Qualifications Rate","spearman":0.1609,"r_squared":0.0006,"slope":-0.39,"intercept":90.6753,"n":4988,"significant":false,"description":"Areas with higher no qualifications rate weakly show higher crime rates","scatterSample":[{"x":20.6,"y":50.95},{"x":22.3,"y":54.02},{"x":25.6,"y":78.29},{"x":23.7,"y":91.16},{"x":22.8,"y":141.61},{"x":26.1,"y":128.08},{"x":26.1,"y":56.0},{"x":25.5,"y":56.85},{"x":28.0,"y":55.76},{"x":26.1,"y":98.95},{"x":24.2,"y":70.63},{"x":20.2,"y":88.28},{"x":18.0,"y":41.98},{"x":21.5,"y":62.84},{"x":12.4,"y":69.49},{"x":26.0,"y":115.63},{"x":17.5,"y":59.49},{"x":18.1,"y":84.47},{"x":7.6,"y":39.13},{"x":12.1,"y":70.98},{"x":13.5,"y":49.16},{"x":11.8,"y":79.95},{"x":17.0,"y":40.07},{"x":21.3,"y":44.33},{"x":14.3,"y":69.14},{"x":14.7,"y":46.22},{"x":16.6,"y":100.8},{"x":14.6,"y":56.33},{"x":12.3,"y":33.01},{"x":10.3,"y":35.16},{"x":13.3,"y":38.76},{"x":17.0,"y":41.52},{"x":26.8,"y":21.82},{"x":22.3,"y":57.68},{"x":16.4,"y":43.15},{"x":22.3,"y":85.03},{"x":17.3,"y":22.97},{"x":16.7,"y":28.54},{"x":18.0,"y":211.52},{"x":20.8,"y":30.69},{"x":16.7,"y":45.56},{"x":19.3,"y":26.44},{"x":22.6,"y":28.88},{"x":19.4,"y":43.85},{"x":22.8,"y":139.79},{"x":16.9,"y":10.56},{"x":22.1,"y":112.08},{"x":12.7,"y":35.93},{"x":15.7,"y":29.11},{"x":15.9,"y":79.84},{"x":27.8,"y":27.31},{"x":17.4,"y":39.69},{"x":15.6,"y":134.39},{"x":21.0,"y":51.7},{"x":29.1,"y":203.35},{"x":21.1,"y":50.17},{"x":19.2,"y":86.38},{"x":18.4,"y":34.79},{"x":11.1,"y":58.47},{"x":17.1,"y":95.03},{"x":18.3,"y":45.0},{"x":18.8,"y":40.55},{"x":11.5,"y":37.9},{"x":26.1,"y":73.39},{"x":22.1,"y":31.65},{"x":23.7,"y":45.9},{"x":26.2,"y":86.62},{"x":25.5,"y":59.25},{"x":7.9,"y":40.0},{"x":14.0,"y":28.48},{"x":17.6,"y":42.09},{"x":7.1,"y":47.31},{"x":14.9,"y":25.81},{"x":12.5,"y":63.47},{"x":10.1,"y":35.42},{"x":6.9,"y":49.17},{"x":18.3,"y":179.58},{"x":23.4,"y":146.28},{"x":19.3,"y":91.88},{"x":19.4,"y":63.58},{"x":13.7,"y":75.53},{"x":12.3,"y":71.11},{"x":15.0,"y":61.17},{"x":13.2,"y":26.33},{"x":13.9,"y":18.59},{"x":10.4,"y":44.91},{"x":10.4,"y":30.72},{"x":13.4,"y":53.31},{"x":11.1,"y":23.5},{"x":15.8,"y":32.19},{"x":5.9,"y":73.42},{"x":13.0,"y":79.46},{"x":8.9,"y":73.02},{"x":5.7,"y":41.78},{"x":21.2,"y":48.02},{"x":10.7,"y":238.97},{"x":17.0,"y":73.5},{"x":12.3,"y":193.74},{"x":19.3,"y":51.51},{"x":20.6,"y":64.11},{"x":11.8,"y":186.33},{"x":10.6,"y":76.52},{"x":4.4,"y":35.29},{"x":11.1,"y":66.52},{"x":20.2,"y":55.73},{"x":22.2,"y":60.34},{"x":18.1,"y":41.56},{"x":22.0,"y":144.97},{"x":18.2,"y":36.44},{"x":8.8,"y":25.41},{"x":12.4,"y":66.82},{"x":28.7,"y":61.39},{"x":16.7,"y":52.44},{"x":14.7,"y":44.26},{"x":24.9,"y":86.12},{"x":15.5,"y":48.84},{"x":14.8,"y":200.5},{"x":16.3,"y":61.21},{"x":24.0,"y":112.09},{"x":13.0,"y":62.01},{"x":13.4,"y":29.78},{"x":17.5,"y":61.01},{"x":19.9,"y":100.87},{"x":21.9,"y":70.16},{"x":17.9,"y":92.27},{"x":19.9,"y":61.9},{"x":15.9,"y":86.27},{"x":15.3,"y":52.32},{"x":23.3,"y":76.05},{"x":26.0,"y":104.52},{"x":7.8,"y":33.71},{"x":7.2,"y":67.61},{"x":9.6,"y":83.87},{"x":13.1,"y":38.92},{"x":20.2,"y":42.28},{"x":9.3,"y":47.16},{"x":24.3,"y":28.41},{"x":22.1,"y":50.51},{"x":7.8,"y":37.77},{"x":18.4,"y":52.77},{"x":23.8,"y":74.91},{"x":22.3,"y":99.68},{"x":24.8,"y":50.52},{"x":21.8,"y":50.63},{"x":13.2,"y":121.11},{"x":30.3,"y":46.14},{"x":29.0,"y":52.45},{"x":5.7,"y":33.76},{"x":21.3,"y":56.71},{"x":19.4,"y":66.58},{"x":21.1,"y":69.81},{"x":19.0,"y":70.69},{"x":31.5,"y":186.93},{"x":27.2,"y":62.6},{"x":23.7,"y":47.9},{"x":15.8,"y":53.57},{"x":26.6,"y":58.56},{"x":18.2,"y":41.35},{"x":32.2,"y":59.8},{"x":27.1,"y":58.88},{"x":16.0,"y":104.95},{"x":16.5,"y":92.67},{"x":13.1,"y":51.18},{"x":10.6,"y":30.66},{"x":15.9,"y":85.52},{"x":27.0,"y":84.36},{"x":30.4,"y":202.62},{"x":13.8,"y":48.83},{"x":23.2,"y":82.3},{"x":15.1,"y":48.39},{"x":17.1,"y":60.31},{"x":11.8,"y":62.62},{"x":15.3,"y":81.04},{"x":28.1,"y":74.16},{"x":21.8,"y":69.2},{"x":21.7,"y":64.34},{"x":15.5,"y":72.93},{"x":27.7,"y":113.61},{"x":15.9,"y":77.71},{"x":19.9,"y":79.49},{"x":26.3,"y":59.93},{"x":17.5,"y":99.55},{"x":23.7,"y":58.87},{"x":16.6,"y":120.38},{"x":18.8,"y":97.13},{"x":22.1,"y":52.37},{"x":13.2,"y":93.91},{"x":11.7,"y":145.08},{"x":14.9,"y":61.48},{"x":29.6,"y":45.82},{"x":40.0,"y":154.22},{"x":21.7,"y":89.93},{"x":7.3,"y":83.71},{"x":21.7,"y":75.48},{"x":16.0,"y":171.17},{"x":12.8,"y":105.17},{"x":9.5,"y":60.57},{"x":26.0,"y":103.54},{"x":15.5,"y":141.11},{"x":15.3,"y":89.2},{"x":9.6,"y":54.32},{"x":18.2,"y":65.5},{"x":15.2,"y":204.97},{"x":6.9,"y":75.67},{"x":15.6,"y":115.08},{"x":5.2,"y":42.77},{"x":23.1,"y":70.72},{"x":5.7,"y":54.18},{"x":24.4,"y":91.54},{"x":6.0,"y":47.47},{"x":9.3,"y":36.48},{"x":22.8,"y":134.14},{"x":8.9,"y":44.09},{"x":11.0,"y":168.82},{"x":20.2,"y":281.43},{"x":28.3,"y":88.91},{"x":31.6,"y":37.69},{"x":12.4,"y":55.06},{"x":21.2,"y":208.46},{"x":23.8,"y":182.46},{"x":22.2,"y":96.71},{"x":29.4,"y":57.33},{"x":22.8,"y":149.81},{"x":19.1,"y":48.88},{"x":28.1,"y":44.06},{"x":13.2,"y":76.46},{"x":18.1,"y":33.72},{"x":12.9,"y":30.96},{"x":15.4,"y":41.52},{"x":25.8,"y":34.06},{"x":14.1,"y":38.96},{"x":12.1,"y":35.13},{"x":19.9,"y":29.3},{"x":14.8,"y":74.69},{"x":21.8,"y":117.1},{"x":13.6,"y":35.54},{"x":14.5,"y":30.75},{"x":24.2,"y":50.52},{"x":17.9,"y":13.83},{"x":19.9,"y":39.12},{"x":15.6,"y":34.83},{"x":23.9,"y":58.86},{"x":21.7,"y":38.12},{"x":18.7,"y":72.55},{"x":26.4,"y":44.88},{"x":14.5,"y":26.02},{"x":18.5,"y":42.03},{"x":20.3,"y":60.99},{"x":21.9,"y":45.21},{"x":18.6,"y":442.65},{"x":20.8,"y":38.76},{"x":23.0,"y":96.27},{"x":14.6,"y":47.59},{"x":23.8,"y":67.14},{"x":23.7,"y":66.54},{"x":25.8,"y":87.52},{"x":22.9,"y":88.24},{"x":8.0,"y":9.71},{"x":19.9,"y":45.45},{"x":21.5,"y":102.98},{"x":11.5,"y":26.44},{"x":14.9,"y":25.56},{"x":7.4,"y":19.63},{"x":15.8,"y":101.43},{"x":13.2,"y":47.78},{"x":22.6,"y":264.72},{"x":15.5,"y":38.17},{"x":25.8,"y":95.34},{"x":18.5,"y":59.83},{"x":23.7,"y":56.53},{"x":22.4,"y":61.15},{"x":10.9,"y":70.65},{"x":10.4,"y":56.56},{"x":22.3,"y":41.37},{"x":30.1,"y":65.52},{"x":25.4,"y":67.97},{"x":18.9,"y":75.4},{"x":24.6,"y":70.13},{"x":25.1,"y":68.3},{"x":18.1,"y":108.14},{"x":17.1,"y":29.49},{"x":18.9,"y":64.59},{"x":17.2,"y":128.38},{"x":15.7,"y":178.64},{"x":22.1,"y":60.66},{"x":13.4,"y":78.17},{"x":23.5,"y":71.48},{"x":16.9,"y":126.04},{"x":20.1,"y":99.06},{"x":20.7,"y":97.2},{"x":13.0,"y":64.77},{"x":10.6,"y":77.46},{"x":12.2,"y":87.44},{"x":16.5,"y":70.04},{"x":7.9,"y":65.98},{"x":9.7,"y":81.94},{"x":14.5,"y":81.55},{"x":7.0,"y":106.24},{"x":6.3,"y":96.72},{"x":6.0,"y":52.63},{"x":8.8,"y":119.17},{"x":13.5,"y":151.43},{"x":5.8,"y":187.03},{"x":11.3,"y":75.84},{"x":4.6,"y":161.6},{"x":5.1,"y":82.95},{"x":9.5,"y":447.8},{"x":6.4,"y":178.99},{"x":8.5,"y":29.5},{"x":8.5,"y":74.88},{"x":18.8,"y":43.74},{"x":16.1,"y":68.29},{"x":15.5,"y":56.71},{"x":7.8,"y":43.37},{"x":13.9,"y":50.4},{"x":17.1,"y":55.21},{"x":8.2,"y":26.02},{"x":14.8,"y":53.49},{"x":7.1,"y":70.88},{"x":20.2,"y":90.99},{"x":4.3,"y":110.34},{"x":3.5,"y":155.24},{"x":21.5,"y":74.04},{"x":15.8,"y":56.89},{"x":17.6,"y":82.67},{"x":20.5,"y":69.35},{"x":10.4,"y":49.1},{"x":18.8,"y":108.4},{"x":9.7,"y":243.99},{"x":13.0,"y":72.38},{"x":11.6,"y":55.67},{"x":8.7,"y":73.95},{"x":17.8,"y":41.8},{"x":13.6,"y":53.53},{"x":4.7,"y":35.71},{"x":6.9,"y":56.25},{"x":17.0,"y":124.42},{"x":17.0,"y":48.68},{"x":21.1,"y":105.26},{"x":14.6,"y":108.85},{"x":7.2,"y":57.06},{"x":15.9,"y":68.02},{"x":10.8,"y":114.12},{"x":23.7,"y":72.91},{"x":22.1,"y":61.43},{"x":8.5,"y":47.84},{"x":11.9,"y":34.65},{"x":9.0,"y":51.63},{"x":22.1,"y":80.17},{"x":19.7,"y":78.68},{"x":14.4,"y":96.92},{"x":14.5,"y":139.34},{"x":11.4,"y":56.67},{"x":17.8,"y":93.24},{"x":23.4,"y":88.57},{"x":8.6,"y":52.23},{"x":15.4,"y":15.48},{"x":21.3,"y":98.37},{"x":4.8,"y":21.98},{"x":15.2,"y":55.56},{"x":6.2,"y":75.32},{"x":18.4,"y":48.16},{"x":16.0,"y":20.9},{"x":17.9,"y":46.01},{"x":21.7,"y":52.0},{"x":19.1,"y":87.06},{"x":5.8,"y":256.55},{"x":7.3,"y":40.4},{"x":3.9,"y":36.9},{"x":21.8,"y":42.65},{"x":21.1,"y":47.23},{"x":26.7,"y":72.28},{"x":24.0,"y":92.11},{"x":22.7,"y":81.89},{"x":25.0,"y":48.21},{"x":16.3,"y":70.3},{"x":21.0,"y":67.0},{"x":24.9,"y":48.42},{"x":25.7,"y":158.81},{"x":28.0,"y":31.22},{"x":26.8,"y":52.56},{"x":25.5,"y":27.41},{"x":22.4,"y":77.04},{"x":23.8,"y":76.88},{"x":20.5,"y":41.65},{"x":15.8,"y":28.01},{"x":19.6,"y":58.46},{"x":14.8,"y":49.54},{"x":9.2,"y":56.81},{"x":12.7,"y":39.66},{"x":24.6,"y":87.95},{"x":15.5,"y":131.94},{"x":16.7,"y":42.3},{"x":20.9,"y":70.4},{"x":17.7,"y":49.43},{"x":22.3,"y":88.67},{"x":16.1,"y":30.28},{"x":13.4,"y":33.72},{"x":14.8,"y":65.67},{"x":17.6,"y":58.92},{"x":20.1,"y":144.7},{"x":12.8,"y":50.07},{"x":4.8,"y":65.48},{"x":5.5,"y":34.92},{"x":13.3,"y":68.95},{"x":19.8,"y":61.17},{"x":5.1,"y":45.01},{"x":11.0,"y":59.51},{"x":6.3,"y":109.46},{"x":13.3,"y":39.28},{"x":4.7,"y":53.61},{"x":4.9,"y":19.77},{"x":4.9,"y":23.35},{"x":7.3,"y":51.89},{"x":14.4,"y":45.73},{"x":14.1,"y":58.36},{"x":18.6,"y":82.32},{"x":12.2,"y":51.39},{"x":8.2,"y":65.68},{"x":8.3,"y":35.2},{"x":19.6,"y":191.4},{"x":25.3,"y":103.27},{"x":16.3,"y":80.06},{"x":19.0,"y":110.06},{"x":7.4,"y":77.56},{"x":14.9,"y":96.36},{"x":17.4,"y":76.54},{"x":8.9,"y":58.3},{"x":29.8,"y":51.09},{"x":16.7,"y":81.92},{"x":7.8,"y":34.85},{"x":14.0,"y":34.56},{"x":10.5,"y":35.1},{"x":10.9,"y":45.84},{"x":18.4,"y":37.34},{"x":14.3,"y":65.23},{"x":20.6,"y":146.51},{"x":10.4,"y":86.85},{"x":17.7,"y":45.48},{"x":12.7,"y":64.42},{"x":15.4,"y":76.58},{"x":11.8,"y":56.58},{"x":21.2,"y":73.24},{"x":11.3,"y":25.66},{"x":17.4,"y":177.54},{"x":22.4,"y":56.17},{"x":14.3,"y":66.26},{"x":14.4,"y":101.96},{"x":25.3,"y":70.52},{"x":25.2,"y":107.56},{"x":3.8,"y":30.7},{"x":18.1,"y":128.61},{"x":23.0,"y":90.85},{"x":16.7,"y":139.04},{"x":20.0,"y":101.41},{"x":16.9,"y":66.63},{"x":18.9,"y":101.87},{"x":18.5,"y":48.02},{"x":17.9,"y":43.48},{"x":16.0,"y":52.93},{"x":15.6,"y":55.16},{"x":12.4,"y":23.63},{"x":18.7,"y":46.62},{"x":17.1,"y":57.11},{"x":21.4,"y":65.6},{"x":26.0,"y":66.13},{"x":20.8,"y":87.6},{"x":17.4,"y":81.43},{"x":22.8,"y":99.63},{"x":15.6,"y":56.05},{"x":20.0,"y":61.94},{"x":4.0,"y":55.78},{"x":9.4,"y":60.85},{"x":6.2,"y":33.2},{"x":5.6,"y":63.44},{"x":12.0,"y":73.39},{"x":12.7,"y":100.28},{"x":18.5,"y":94.24},{"x":8.1,"y":27.98},{"x":6.0,"y":64.63},{"x":8.6,"y":80.58},{"x":19.6,"y":100.95},{"x":13.5,"y":112.87},{"x":17.7,"y":68.25},{"x":5.7,"y":79.54},{"x":15.2,"y":104.87},{"x":8.7,"y":56.43},{"x":17.1,"y":65.95},{"x":8.9,"y":58.58},{"x":8.5,"y":56.01},{"x":10.0,"y":334.87},{"x":29.0,"y":60.49},{"x":7.7,"y":205.79},{"x":8.5,"y":147.32},{"x":7.8,"y":93.28},{"x":8.2,"y":178.57},{"x":21.3,"y":65.18},{"x":5.1,"y":363.64},{"x":8.4,"y":74.72},{"x":13.0,"y":83.7},{"x":8.8,"y":2136.41},{"x":17.1,"y":59.19},{"x":13.1,"y":40.36},{"x":2.0,"y":31.76},{"x":9.9,"y":118.17},{"x":5.6,"y":25.27},{"x":8.8,"y":30.21},{"x":10.4,"y":146.87},{"x":5.3,"y":58.42},{"x":9.8,"y":35.0},{"x":22.7,"y":133.09},{"x":8.6,"y":105.12},{"x":12.7,"y":189.33},{"x":16.9,"y":48.42},{"x":15.0,"y":97.8},{"x":9.6,"y":130.76},{"x":10.4,"y":137.56},{"x":13.1,"y":144.32},{"x":6.1,"y":192.69},{"x":18.9,"y":118.39},{"x":16.5,"y":148.15},{"x":25.9,"y":51.3},{"x":15.1,"y":34.59},{"x":23.5,"y":74.1},{"x":11.8,"y":59.99},{"x":10.7,"y":110.82},{"x":17.3,"y":91.67},{"x":18.9,"y":96.45},{"x":11.5,"y":287.47},{"x":26.5,"y":97.04},{"x":9.0,"y":101.5},{"x":5.0,"y":32.87},{"x":20.8,"y":54.6},{"x":12.3,"y":61.85},{"x":3.5,"y":58.36},{"x":4.3,"y":27.45},{"x":8.4,"y":36.75},{"x":23.2,"y":51.37},{"x":20.1,"y":58.05},{"x":24.2,"y":55.06},{"x":22.1,"y":77.48},{"x":15.2,"y":92.85},{"x":16.1,"y":125.0},{"x":12.4,"y":136.12},{"x":7.6,"y":162.13},{"x":11.3,"y":88.95},{"x":9.3,"y":176.11},{"x":6.5,"y":80.03},{"x":18.4,"y":85.76},{"x":23.8,"y":91.14},{"x":29.2,"y":81.98},{"x":19.8,"y":127.88},{"x":4.1,"y":84.01},{"x":13.1,"y":89.95},{"x":13.0,"y":148.26}]}],"meta":{"n_lsoa":4988,"method":"Spearman rank correlation + simple OLS regression","crime_variable":"crime_rate_per_1000","data_year":"2021 Census + 2025 Q4 Crime"}}