{"Barking and Dagenham":{"unemployment":4.7,"deprived":19.1,"noQual":22.7,"highQual":33.3,"weekly_pay":"621.4"},"Barnet":{"unemployment":3.8,"deprived":13.3,"noQual":15.4,"highQual":49,"weekly_pay":"672.9"},"Bexley":{"unemployment":3.2,"deprived":13.9,"noQual":18.2,"highQual":31.6,"weekly_pay":"670.8"},"Brent":{"unemployment":4.5,"deprived":17.7,"noQual":21.7,"highQual":40,"weekly_pay":"612.2"},"Bromley":{"unemployment":3,"deprived":11.3,"noQual":13.8,"highQual":42.8,"weekly_pay":"773.0"},"Camden":{"unemployment":4,"deprived":14.6,"noQual":11.8,"highQual":57.3,"weekly_pay":"776.8"},"City of London":{"unemployment":3.5,"deprived":7.1,"noQual":6.6,"highQual":74.2,"weekly_pay":"#"},"Croydon":{"unemployment":4.1,"deprived":14.1,"noQual":16.1,"highQual":41,"weekly_pay":"687.7"},"Ealing":{"unemployment":4.4,"deprived":15.2,"noQual":17.9,"highQual":44.3,"weekly_pay":"643.9"},"Enfield":{"unemployment":4.1,"deprived":16.7,"noQual":22.5,"highQual":36.3,"weekly_pay":"636.8"},"Greenwich":{"unemployment":4.5,"deprived":14.6,"noQual":16.7,"highQual":45.7,"weekly_pay":"702.0"},"Hackney":{"unemployment":4.7,"deprived":16,"noQual":16.7,"highQual":52.4,"weekly_pay":"683.5"},"Hammersmith and Fulham":{"unemployment":4.3,"deprived":13,"noQual":11.9,"highQual":57.6,"weekly_pay":"776.2"},"Haringey":{"unemployment":4.9,"deprived":16.8,"noQual":18.5,"highQual":48.3,"weekly_pay":"692.5"},"Harrow":{"unemployment":3.5,"deprived":13.4,"noQual":17.4,"highQual":45,"weekly_pay":"706.1"},"Havering":{"unemployment":3.2,"deprived":14.7,"noQual":20,"highQual":29.5,"weekly_pay":"670.8"},"Hillingdon":{"unemployment":3.9,"deprived":15.1,"noQual":18.2,"highQual":37.5,"weekly_pay":"676.4"},"Hounslow":{"unemployment":4.5,"deprived":16,"noQual":18.6,"highQual":41.6,"weekly_pay":"639.5"},"Islington":{"unemployment":4.5,"deprived":15.1,"noQual":13.8,"highQual":56.6,"weekly_pay":"776.6"},"Kensington and Chelsea":{"unemployment":4,"deprived":12.1,"noQual":11.4,"highQual":59.5,"weekly_pay":"967.8"},"Kingston upon Thames":{"unemployment":3,"deprived":10.7,"noQual":11.9,"highQual":51.4,"weekly_pay":"755.6"},"Lambeth":{"unemployment":4.6,"deprived":13.8,"noQual":13.1,"highQual":56.3,"weekly_pay":"732.3"},"Lewisham":{"unemployment":4.9,"deprived":15.2,"noQual":14.6,"highQual":49.8,"weekly_pay":"678.0"},"Merton":{"unemployment":3.5,"deprived":11.8,"noQual":14.2,"highQual":50,"weekly_pay":"670.8"},"Newham":{"unemployment":5,"deprived":18.4,"noQual":20.7,"highQual":40.2,"weekly_pay":"667.5"},"Redbridge":{"unemployment":3.8,"deprived":14.8,"noQual":17.3,"highQual":42.4,"weekly_pay":"673.6"},"Richmond upon Thames":{"unemployment":3,"deprived":8.7,"noQual":9.1,"highQual":60.4,"weekly_pay":"776.2"},"Southwark":{"unemployment":4.6,"deprived":14.5,"noQual":13.9,"highQual":54.9,"weekly_pay":"723.5"},"Sutton":{"unemployment":2.9,"deprived":12.7,"noQual":15.2,"highQual":39.8,"weekly_pay":"676.7"},"Tower Hamlets":{"unemployment":4.7,"deprived":15.5,"noQual":16.2,"highQual":50.3,"weekly_pay":"784.4"},"Waltham Forest":{"unemployment":4.5,"deprived":16.1,"noQual":18.2,"highQual":43.2,"weekly_pay":"689.9"},"Wandsworth":{"unemployment":3.4,"deprived":10.5,"noQual":9.9,"highQual":62.6,"weekly_pay":"822.2"},"Westminster":{"unemployment":4,"deprived":13.4,"noQual":12.9,"highQual":57.7,"weekly_pay":"830.5"}}
